Workbook

Sheet Supuestos
A1: Supuestos — Planta solar para autoconsumo (ficticio)
A2: Celdas en azul: supuestos (editables). El resto del libro se calcula con fórmulas.
A4: Tasa de descuento | B4: 0.1
A5: Horizonte (años) | B5: 10
A6: Tasa de impuesto | B6: 0.27
A7: Capital de trabajo (% ingresos del año siguiente) | B7: 0.05
A8: Moneda | B8: CLP
A9: Tipo de evaluación | B9: privada
A11: Inversiones
A12: Concepto | B12: Año | C12: Monto
A13: Paneles e inversores | B13: 0 | C13: 180000000
A14: Obras e instalación | B14: 0 | C14: 40000000
A15: Recambio de inversores | B15: 6 | C15: 15000000
A17: Ingresos
A18: Concepto | B18: Año inicio | C18: Monto anual | D18: Crecimiento anual
A19: Ahorro en energía | B19: 1 | C19: 42000000 | D19: 0.03
A20: Venta de excedentes | B20: 1 | C20: 6000000 | D20: 0
A22: Costos
A23: Concepto | B23: Año inicio | C23: Monto anual | D23: Crecimiento anual
A24: Operación y mantención | B24: 1 | C24: 5500000 | D24: 0.03
A26: Depreciación
A27: Activo | B27: Monto depreciable | C27: Vida útil (años)
A28: Paneles e inversores | B28: 180000000 | C28: 10
A29: Obras e instalación | B29: 40000000 | C29: 20
A31: Valor residual: método (valor_libro | monto | ninguno) | B31: valor_libro
A32: Valor residual: monto (si el método es 'monto') | B32: 0
A34: - Año 0 = inversión inicial; flujos al final de cada año.
A35: - Impuesto = tasa × utilidad antes de impuesto cuando es positiva (sin arrastre de pérdidas: simplificación).
A36: - Capital de trabajo requerido en el año t = % × ingresos del año t+1; se recupera al final del horizonte.
A37: - Valor residual al final del horizonte: valor libro (inversión − depreciación acumulada), un monto dado, o ninguno.
A38: - Evaluación social: usar tasa social y precios sociales según la metodología oficial aplicable (tasa de impuesto 0).

Sheet Flujo
A1: Flujo de caja
A3: Concepto | B3: 0 | C3: 1 | D3: 2 | E3: 3 | F3: 4 | G3: 5 | H3: 6 | I3: 7 | J3: 8 | K3: 9 | L3: 10
A4: Ingreso: Ahorro en energía | B4: =IF(B$3>=Supuestos!$B$19,Supuestos!$C$19*(1+Supuestos!$D$19)^(B$3-Supuestos!$B$19),0) -> 0 | C4: =IF(C$3>=Supuestos!$B$19,Supuestos!$C$19*(1+Supuestos!$D$19)^(C$3-Supuestos!$B$19),0) -> 42000000 | D4: =IF(D$3>=Supuestos!$B$19,Supuestos!$C$19*(1+Supuestos!$D$19)^(D$3-Supuestos!$B$19),0) -> 43260000 | E4: =IF(E$3>=Supuestos!$B$19,Supuestos!$C$19*(1+Supuestos!$D$19)^(E$3-Supuestos!$B$19),0) -> 44557800 | F4: =IF(F$3>=Supuestos!$B$19,Supuestos!$C$19*(1+Supuestos!$D$19)^(F$3-Supuestos!$B$19),0) -> 45894534 | G4: =IF(G$3>=Supuestos!$B$19,Supuestos!$C$19*(1+Supuestos!$D$19)^(G$3-Supuestos!$B$19),0) -> 47271370 | H4: =IF(H$3>=Supuestos!$B$19,Supuestos!$C$19*(1+Supuestos!$D$19)^(H$3-Supuestos!$B$19),0) -> 48689511 | I4: =IF(I$3>=Supuestos!$B$19,Supuestos!$C$19*(1+Supuestos!$D$19)^(I$3-Supuestos!$B$19),0) -> 50150196 | ... L4: =IF(L$3>=Supuestos!$B$19,Supuestos!$C$19*(1+Supuestos!$D$19)^(L$3-Supuestos!$B$19),0) -> 54800474
A5: Ingreso: Venta de excedentes | B5: =IF(B$3>=Supuestos!$B$20,Supuestos!$C$20*(1+Supuestos!$D$20)^(B$3-Supuestos!$B$20),0) -> 0 | C5: =IF(C$3>=Supuestos!$B$20,Supuestos!$C$20*(1+Supuestos!$D$20)^(C$3-Supuestos!$B$20),0) -> 6000000 | D5: =IF(D$3>=Supuestos!$B$20,Supuestos!$C$20*(1+Supuestos!$D$20)^(D$3-Supuestos!$B$20),0) -> 6000000 | E5: =IF(E$3>=Supuestos!$B$20,Supuestos!$C$20*(1+Supuestos!$D$20)^(E$3-Supuestos!$B$20),0) -> 6000000 | F5: =IF(F$3>=Supuestos!$B$20,Supuestos!$C$20*(1+Supuestos!$D$20)^(F$3-Supuestos!$B$20),0) -> 6000000 | G5: =IF(G$3>=Supuestos!$B$20,Supuestos!$C$20*(1+Supuestos!$D$20)^(G$3-Supuestos!$B$20),0) -> 6000000 | H5: =IF(H$3>=Supuestos!$B$20,Supuestos!$C$20*(1+Supuestos!$D$20)^(H$3-Supuestos!$B$20),0) -> 6000000 | I5: =IF(I$3>=Supuestos!$B$20,Supuestos!$C$20*(1+Supuestos!$D$20)^(I$3-Supuestos!$B$20),0) -> 6000000 | ... L5: =IF(L$3>=Supuestos!$B$20,Supuestos!$C$20*(1+Supuestos!$D$20)^(L$3-Supuestos!$B$20),0) -> 6000000
A6: Total ingresos | B6: =SUM(B4:B5) -> 0 | C6: =SUM(C4:C5) -> 48000000 | D6: =SUM(D4:D5) -> 49260000 | E6: =SUM(E4:E5) -> 50557800 | F6: =SUM(F4:F5) -> 51894534 | G6: =SUM(G4:G5) -> 53271370 | H6: =SUM(H4:H5) -> 54689511 | I6: =SUM(I4:I5) -> 56150196 | ... L6: =SUM(L4:L5) -> 60800474
A7: Costo: Operación y mantención | B7: =IF(B$3>=Supuestos!$B$24,Supuestos!$C$24*(1+Supuestos!$D$24)^(B$3-Supuestos!$B$24),0) -> 0 | C7: =IF(C$3>=Supuestos!$B$24,Supuestos!$C$24*(1+Supuestos!$D$24)^(C$3-Supuestos!$B$24),0) -> 5500000 | D7: =IF(D$3>=Supuestos!$B$24,Supuestos!$C$24*(1+Supuestos!$D$24)^(D$3-Supuestos!$B$24),0) -> 5665000 | E7: =IF(E$3>=Supuestos!$B$24,Supuestos!$C$24*(1+Supuestos!$D$24)^(E$3-Supuestos!$B$24),0) -> 5834950 | F7: =IF(F$3>=Supuestos!$B$24,Supuestos!$C$24*(1+Supuestos!$D$24)^(F$3-Supuestos!$B$24),0) -> 6009998.5 | G7: =IF(G$3>=Supuestos!$B$24,Supuestos!$C$24*(1+Supuestos!$D$24)^(G$3-Supuestos!$B$24),0) -> 6190298.5 | H7: =IF(H$3>=Supuestos!$B$24,Supuestos!$C$24*(1+Supuestos!$D$24)^(H$3-Supuestos!$B$24),0) -> 6376007.4 | I7: =IF(I$3>=Supuestos!$B$24,Supuestos!$C$24*(1+Supuestos!$D$24)^(I$3-Supuestos!$B$24),0) -> 6567287.6 | ... L7: =IF(L$3>=Supuestos!$B$24,Supuestos!$C$24*(1+Supuestos!$D$24)^(L$3-Supuestos!$B$24),0) -> 7176252.5
A8: Total costos | B8: =SUM(B7:B7) -> 0 | C8: =SUM(C7:C7) -> 5500000 | D8: =SUM(D7:D7) -> 5665000 | E8: =SUM(E7:E7) -> 5834950 | F8: =SUM(F7:F7) -> 6009998.5 | G8: =SUM(G7:G7) -> 6190298.5 | H8: =SUM(H7:H7) -> 6376007.4 | I8: =SUM(I7:I7) -> 6567287.6 | ... L8: =SUM(L7:L7) -> 7176252.5
A9: Depreciación: Paneles e inversores | B9: =IF(AND(B$3>=1,B$3<=Supuestos!$C$28),Supuestos!$B$28/Supuestos!$C$28,0) -> 0 | C9: =IF(AND(C$3>=1,C$3<=Supuestos!$C$28),Supuestos!$B$28/Supuestos!$C$28,0) -> 18000000 | D9: =IF(AND(D$3>=1,D$3<=Supuestos!$C$28),Supuestos!$B$28/Supuestos!$C$28,0) -> 18000000 | E9: =IF(AND(E$3>=1,E$3<=Supuestos!$C$28),Supuestos!$B$28/Supuestos!$C$28,0) -> 18000000 | F9: =IF(AND(F$3>=1,F$3<=Supuestos!$C$28),Supuestos!$B$28/Supuestos!$C$28,0) -> 18000000 | G9: =IF(AND(G$3>=1,G$3<=Supuestos!$C$28),Supuestos!$B$28/Supuestos!$C$28,0) -> 18000000 | H9: =IF(AND(H$3>=1,H$3<=Supuestos!$C$28),Supuestos!$B$28/Supuestos!$C$28,0) -> 18000000 | I9: =IF(AND(I$3>=1,I$3<=Supuestos!$C$28),Supuestos!$B$28/Supuestos!$C$28,0) -> 18000000 | ... L9: =IF(AND(L$3>=1,L$3<=Supuestos!$C$28),Supuestos!$B$28/Supuestos!$C$28,0) -> 18000000
A10: Depreciación: Obras e instalación | B10: =IF(AND(B$3>=1,B$3<=Supuestos!$C$29),Supuestos!$B$29/Supuestos!$C$29,0) -> 0 | C10: =IF(AND(C$3>=1,C$3<=Supuestos!$C$29),Supuestos!$B$29/Supuestos!$C$29,0) -> 2000000 | D10: =IF(AND(D$3>=1,D$3<=Supuestos!$C$29),Supuestos!$B$29/Supuestos!$C$29,0) -> 2000000 | E10: =IF(AND(E$3>=1,E$3<=Supuestos!$C$29),Supuestos!$B$29/Supuestos!$C$29,0) -> 2000000 | F10: =IF(AND(F$3>=1,F$3<=Supuestos!$C$29),Supuestos!$B$29/Supuestos!$C$29,0) -> 2000000 | G10: =IF(AND(G$3>=1,G$3<=Supuestos!$C$29),Supuestos!$B$29/Supuestos!$C$29,0) -> 2000000 | H10: =IF(AND(H$3>=1,H$3<=Supuestos!$C$29),Supuestos!$B$29/Supuestos!$C$29,0) -> 2000000 | I10: =IF(AND(I$3>=1,I$3<=Supuestos!$C$29),Supuestos!$B$29/Supuestos!$C$29,0) -> 2000000 | ... L10: =IF(AND(L$3>=1,L$3<=Supuestos!$C$29),Supuestos!$B$29/Supuestos!$C$29,0) -> 2000000
A11: Total depreciación | B11: =SUM(B9:B10) -> 0 | C11: =SUM(C9:C10) -> 20000000 | D11: =SUM(D9:D10) -> 20000000 | E11: =SUM(E9:E10) -> 20000000 | F11: =SUM(F9:F10) -> 20000000 | G11: =SUM(G9:G10) -> 20000000 | H11: =SUM(H9:H10) -> 20000000 | I11: =SUM(I9:I10) -> 20000000 | ... L11: =SUM(L9:L10) -> 20000000
A12: Utilidad antes de impuesto | B12: =B6-B8-B11 -> 0 | C12: =C6-C8-C11 -> 22500000 | D12: =D6-D8-D11 -> 23595000 | E12: =E6-E8-E11 -> 24722850 | F12: =F6-F8-F11 -> 25884536 | G12: =G6-G8-G11 -> 27081072 | H12: =H6-H8-H11 -> 28313504 | I12: =I6-I8-I11 -> 29582909 | ... L12: =L6-L8-L11 -> 33624221
A13: Impuesto | B13: =MAX(0,B12)*Supuestos!$B$6 -> 0 | C13: =MAX(0,C12)*Supuestos!$B$6 -> 6075000 | D13: =MAX(0,D12)*Supuestos!$B$6 -> 6370650 | E13: =MAX(0,E12)*Supuestos!$B$6 -> 6675169.5 | F13: =MAX(0,F12)*Supuestos!$B$6 -> 6988824.6 | G13: =MAX(0,G12)*Supuestos!$B$6 -> 7311889.3 | H13: =MAX(0,H12)*Supuestos!$B$6 -> 7644646 | I13: =MAX(0,I12)*Supuestos!$B$6 -> 7987385.4 | ... L13: =MAX(0,L12)*Supuestos!$B$6 -> 9078539.7
A14: Utilidad neta | B14: =B12-B13 -> 0 | C14: =C12-C13 -> 16425000 | D14: =D12-D13 -> 17224350 | E14: =E12-E13 -> 18047680 | F14: =F12-F13 -> 18895711 | G14: =G12-G13 -> 19769182 | H14: =H12-H13 -> 20668858 | I14: =I12-I13 -> 21595523 | ... L14: =L12-L13 -> 24545681
A15: (+) Depreciación | B15: =B11 -> 0 | C15: =C11 -> 20000000 | D15: =D11 -> 20000000 | E15: =E11 -> 20000000 | F15: =F11 -> 20000000 | G15: =G11 -> 20000000 | H15: =H11 -> 20000000 | I15: =I11 -> 20000000 | ... L15: =L11 -> 20000000
A16: Inversión: Paneles e inversores | B16: =IF(B$3=Supuestos!$B$13,Supuestos!$C$13,0) -> 180000000 | C16: =IF(C$3=Supuestos!$B$13,Supuestos!$C$13,0) -> 0 | D16: =IF(D$3=Supuestos!$B$13,Supuestos!$C$13,0) -> 0 | E16: =IF(E$3=Supuestos!$B$13,Supuestos!$C$13,0) -> 0 | F16: =IF(F$3=Supuestos!$B$13,Supuestos!$C$13,0) -> 0 | G16: =IF(G$3=Supuestos!$B$13,Supuestos!$C$13,0) -> 0 | H16: =IF(H$3=Supuestos!$B$13,Supuestos!$C$13,0) -> 0 | I16: =IF(I$3=Supuestos!$B$13,Supuestos!$C$13,0) -> 0 | ... L16: =IF(L$3=Supuestos!$B$13,Supuestos!$C$13,0) -> 0
A17: Inversión: Obras e instalación | B17: =IF(B$3=Supuestos!$B$14,Supuestos!$C$14,0) -> 40000000 | C17: =IF(C$3=Supuestos!$B$14,Supuestos!$C$14,0) -> 0 | D17: =IF(D$3=Supuestos!$B$14,Supuestos!$C$14,0) -> 0 | E17: =IF(E$3=Supuestos!$B$14,Supuestos!$C$14,0) -> 0 | F17: =IF(F$3=Supuestos!$B$14,Supuestos!$C$14,0) -> 0 | G17: =IF(G$3=Supuestos!$B$14,Supuestos!$C$14,0) -> 0 | H17: =IF(H$3=Supuestos!$B$14,Supuestos!$C$14,0) -> 0 | I17: =IF(I$3=Supuestos!$B$14,Supuestos!$C$14,0) -> 0 | ... L17: =IF(L$3=Supuestos!$B$14,Supuestos!$C$14,0) -> 0
A18: Inversión: Recambio de inversores | B18: =IF(B$3=Supuestos!$B$15,Supuestos!$C$15,0) -> 0 | C18: =IF(C$3=Supuestos!$B$15,Supuestos!$C$15,0) -> 0 | D18: =IF(D$3=Supuestos!$B$15,Supuestos!$C$15,0) -> 0 | E18: =IF(E$3=Supuestos!$B$15,Supuestos!$C$15,0) -> 0 | F18: =IF(F$3=Supuestos!$B$15,Supuestos!$C$15,0) -> 0 | G18: =IF(G$3=Supuestos!$B$15,Supuestos!$C$15,0) -> 0 | H18: =IF(H$3=Supuestos!$B$15,Supuestos!$C$15,0) -> 15000000 | I18: =IF(I$3=Supuestos!$B$15,Supuestos!$C$15,0) -> 0 | ... L18: =IF(L$3=Supuestos!$B$15,Supuestos!$C$15,0) -> 0
A19: (−) Total inversión | B19: =SUM(B16:B18) -> 220000000 | C19: =SUM(C16:C18) -> 0 | D19: =SUM(D16:D18) -> 0 | E19: =SUM(E16:E18) -> 0 | F19: =SUM(F16:F18) -> 0 | G19: =SUM(G16:G18) -> 0 | H19: =SUM(H16:H18) -> 15000000 | I19: =SUM(I16:I18) -> 0 | ... L19: =SUM(L16:L18) -> 0
A20: Capital de trabajo requerido | B20: =Supuestos!$B$7*C6 -> 2400000 | C20: =Supuestos!$B$7*D6 -> 2463000 | D20: =Supuestos!$B$7*E6 -> 2527890 | E20: =Supuestos!$B$7*F6 -> 2594726.7 | F20: =Supuestos!$B$7*G6 -> 2663568.5 | G20: =Supuestos!$B$7*H6 -> 2734475.6 | H20: =Supuestos!$B$7*I6 -> 2807509.8 | I20: =Supuestos!$B$7*J6 -> 2882735.1 | ... K20: =Supuestos!$B$7*L6 -> 3040023.7 | L20: =0 -> 0
A21: (−) Variación capital de trabajo | B21: =B20 -> 2400000 | C21: =C20-B20 -> 63000 | D21: =D20-C20 -> 64890 | E21: =E20-D20 -> 66836.7 | F21: =F20-E20 -> 68841.801 | G21: =G20-F20 -> 70907.055 | H21: =H20-G20 -> 73034.267 | I21: =I20-H20 -> 75225.295 | J21: =J20-I20 -> 77482.054 | ... L21: =L20-K20 -> -3040023.7
A22: (+) Valor residual | B22: =0 -> 0 | C22: =0 -> 0 | D22: =0 -> 0 | E22: =0 -> 0 | F22: =0 -> 0 | G22: =0 -> 0 | H22: =0 -> 0 | I22: =0 -> 0 | ... K22: =0 -> 0 | L22: =IF(Supuestos!$B$31="valor_libro",SUM($B$19:$L$19)-SUM($C$11:$L$11),IF(Supuestos!$B$31="monto",Supuestos!$B$32,0)) -> 35000000
A23: FLUJO NETO | B23: =B14+B15-B19-B21+B22 -> -222400000 | C23: =C14+C15-C19-C21+C22 -> 36362000 | D23: =D14+D15-D19-D21+D22 -> 37159460 | E23: =E14+E15-E19-E21+E22 -> 37980844 | F23: =F14+F15-F19-F21+F22 -> 38826869 | G23: =G14+G15-G19-G21+G22 -> 39698275 | H23: =H14+H15-H19-H21+H22 -> 25595823 | I23: =I14+I15-I19-I21+I22 -> 41520298 | ... L23: =L14+L15-L19-L21+L22 -> 82585705
A24: Flujo acumulado | B24: =B23 -> -222400000 | C24: =B24+C23 -> -186038000 | D24: =C24+D23 -> -148878540 | E24: =D24+E23 -> -1.108977e+08 | F24: =E24+F23 -> -72070827 | G24: =F24+G23 -> -32372552 | H24: =G24+H23 -> -6776728.5 | I24: =H24+I23 -> 34743570 | J24: =I24+J23 -> 77216077 | ... L24: =K24+L23 -> 2.0325506e+08

Sheet Indicadores
A1: Indicadores
A3: VAN | B3: =Flujo!$B$23+NPV(Supuestos!$B$4,Flujo!$C$23:$L$23) -> 26908200
A4: TIR | B4: =IFERROR(IRR(Flujo!$B$23:$L$23),"No calculable") -> 0.1250986
A5: Período de recuperación (años, flujo acumulado ≥ 0) | B5: =IF(COUNTIF(Flujo!$B$24:$L$24,"<0")>10,"No recupera",COUNTIF(Flujo!$B$24:$L$24,"<0")) -> 7
A6: Inversión total | B6: =SUM(Flujo!$B$19:$L$19) -> 235000000
A7: VAN / inversión | B7: =IFERROR(B3/B6,0) -> 0.11450298
A8: Tasa de descuento | B8: =Supuestos!$B$4 -> 0.1

Sheet Sensibilidad
A1: Sensibilidad del VAN
A2: Cada fila recalcula el flujo con los factores indicados (variación sobre el caso base).
A4: Escenario | B4: Δ ingresos | C4: Δ costos | D4: Δ inversión | E4: Año 0 | F4: Año 1 | G4: Año 2 | H4: Año 3 | I4: Año 4 | J4: Año 5 | K4: Año 6 | L4: Año 7 | M4: Año 8 | N4: Año 9 | O4: Año 10 | P4: VAN
A5: Base | B5: 0 | C5: 0 | D5: 0 | E5: =(Flujo!B$6*(1+$B5)-Flujo!B$8*(1+$C5)-Flujo!B$11*(1+$D5))-MAX(0,(Flujo!B$6*(1+$B5)-Flujo!B$8*(1+$C5)-Flujo!B$11*(1+$D5)))*Supuestos!$B$6+Flujo!B$11*(1+$D5)-Flujo!B$19*(1+$D5)-Flujo!B$21*(1+$B5) -> -222400000 | F5: =(Flujo!C$6*(1+$B5)-Flujo!C$8*(1+$C5)-Flujo!C$11*(1+$D5))-MAX(0,(Flujo!C$6*(1+$B5)-Flujo!C$8*(1+$C5)-Flujo!C$11*(1+$D5)))*Supuestos!$B$6+Flujo!C$11*(1+$D5)-Flujo!C$19*(1+$D5)-Flujo!C$21*(1+$B5) -> 36362000 | G5: =(Flujo!D$6*(1+$B5)-Flujo!D$8*(1+$C5)-Flujo!D$11*(1+$D5))-MAX(0,(Flujo!D$6*(1+$B5)-Flujo!D$8*(1+$C5)-Flujo!D$11*(1+$D5)))*Supuestos!$B$6+Flujo!D$11*(1+$D5)-Flujo!D$19*(1+$D5)-Flujo!D$21*(1+$B5) -> 37159460 | H5: =(Flujo!E$6*(1+$B5)-Flujo!E$8*(1+$C5)-Flujo!E$11*(1+$D5))-MAX(0,(Flujo!E$6*(1+$B5)-Flujo!E$8*(1+$C5)-Flujo!E$11*(1+$D5)))*Supuestos!$B$6+Flujo!E$11*(1+$D5)-Flujo!E$19*(1+$D5)-Flujo!E$21*(1+$B5) -> 37980844 | I5: =(Flujo!F$6*(1+$B5)-Flujo!F$8*(1+$C5)-Flujo!F$11*(1+$D5))-MAX(0,(Flujo!F$6*(1+$B5)-Flujo!F$8*(1+$C5)-Flujo!F$11*(1+$D5)))*Supuestos!$B$6+Flujo!F$11*(1+$D5)-Flujo!F$19*(1+$D5)-Flujo!F$21*(1+$B5) -> 38826869 | J5: =(Flujo!G$6*(1+$B5)-Flujo!G$8*(1+$C5)-Flujo!G$11*(1+$D5))-MAX(0,(Flujo!G$6*(1+$B5)-Flujo!G$8*(1+$C5)-Flujo!G$11*(1+$D5)))*Supuestos!$B$6+Flujo!G$11*(1+$D5)-Flujo!G$19*(1+$D5)-Flujo!G$21*(1+$B5) -> 39698275 | K5: =(Flujo!H$6*(1+$B5)-Flujo!H$8*(1+$C5)-Flujo!H$11*(1+$D5))-MAX(0,(Flujo!H$6*(1+$B5)-Flujo!H$8*(1+$C5)-Flujo!H$11*(1+$D5)))*Supuestos!$B$6+Flujo!H$11*(1+$D5)-Flujo!H$19*(1+$D5)-Flujo!H$21*(1+$B5) -> 25595823 | L5: =(Flujo!I$6*(1+$B5)-Flujo!I$8*(1+$C5)-Flujo!I$11*(1+$D5))-MAX(0,(Flujo!I$6*(1+$B5)-Flujo!I$8*(1+$C5)-Flujo!I$11*(1+$D5)))*Supuestos!$B$6+Flujo!I$11*(1+$D5)-Flujo!I$19*(1+$D5)-Flujo!I$21*(1+$B5) -> 41520298 | ... N5: =(Flujo!K$6*(1+$B5)-Flujo!K$8*(1+$C5)-Flujo!K$11*(1+$D5))-MAX(0,(Flujo!K$6*(1+$B5)-Flujo!K$8*(1+$C5)-Flujo!K$11*(1+$D5)))*Supuestos!$B$6+Flujo!K$11*(1+$D5)-Flujo!K$19*(1+$D5)-Flujo!K$21*(1+$B5) -> 43453282 | O5: =(Flujo!L$6*(1+$B5)-Flujo!L$8*(1+$C5)-Flujo!L$11*(1+$D5))-MAX(0,(Flujo!L$6*(1+$B5)-Flujo!L$8*(1+$C5)-Flujo!L$11*(1+$D5)))*Supuestos!$B$6+Flujo!L$11*(1+$D5)-Flujo!L$19*(1+$D5)-Flujo!L$21*(1+$B5)+Flujo!L$22*IF(Supuestos!$B$31="valor_libro",1+$D5,1) -> 82585705 | P5: =E5+NPV(Supuestos!$B$4,F5:O5) -> 26908200
A6: ingresos -20% | B6: -0.2 | C6: 0 | D6: 0 | E6: =(Flujo!B$6*(1+$B6)-Flujo!B$8*(1+$C6)-Flujo!B$11*(1+$D6))-MAX(0,(Flujo!B$6*(1+$B6)-Flujo!B$8*(1+$C6)-Flujo!B$11*(1+$D6)))*Supuestos!$B$6+Flujo!B$11*(1+$D6)-Flujo!B$19*(1+$D6)-Flujo!B$21*(1+$B6) -> -221920000 | F6: =(Flujo!C$6*(1+$B6)-Flujo!C$8*(1+$C6)-Flujo!C$11*(1+$D6))-MAX(0,(Flujo!C$6*(1+$B6)-Flujo!C$8*(1+$C6)-Flujo!C$11*(1+$D6)))*Supuestos!$B$6+Flujo!C$11*(1+$D6)-Flujo!C$19*(1+$D6)-Flujo!C$21*(1+$B6) -> 29366600 | G6: =(Flujo!D$6*(1+$B6)-Flujo!D$8*(1+$C6)-Flujo!D$11*(1+$D6))-MAX(0,(Flujo!D$6*(1+$B6)-Flujo!D$8*(1+$C6)-Flujo!D$11*(1+$D6)))*Supuestos!$B$6+Flujo!D$11*(1+$D6)-Flujo!D$19*(1+$D6)-Flujo!D$21*(1+$B6) -> 29980478 | H6: =(Flujo!E$6*(1+$B6)-Flujo!E$8*(1+$C6)-Flujo!E$11*(1+$D6))-MAX(0,(Flujo!E$6*(1+$B6)-Flujo!E$8*(1+$C6)-Flujo!E$11*(1+$D6)))*Supuestos!$B$6+Flujo!E$11*(1+$D6)-Flujo!E$19*(1+$D6)-Flujo!E$21*(1+$B6) -> 30612772 | I6: =(Flujo!F$6*(1+$B6)-Flujo!F$8*(1+$C6)-Flujo!F$11*(1+$D6))-MAX(0,(Flujo!F$6*(1+$B6)-Flujo!F$8*(1+$C6)-Flujo!F$11*(1+$D6)))*Supuestos!$B$6+Flujo!F$11*(1+$D6)-Flujo!F$19*(1+$D6)-Flujo!F$21*(1+$B6) -> 31264036 | J6: =(Flujo!G$6*(1+$B6)-Flujo!G$8*(1+$C6)-Flujo!G$11*(1+$D6))-MAX(0,(Flujo!G$6*(1+$B6)-Flujo!G$8*(1+$C6)-Flujo!G$11*(1+$D6)))*Supuestos!$B$6+Flujo!G$11*(1+$D6)-Flujo!G$19*(1+$D6)-Flujo!G$21*(1+$B6) -> 31934837 | K6: =(Flujo!H$6*(1+$B6)-Flujo!H$8*(1+$C6)-Flujo!H$11*(1+$D6))-MAX(0,(Flujo!H$6*(1+$B6)-Flujo!H$8*(1+$C6)-Flujo!H$11*(1+$D6)))*Supuestos!$B$6+Flujo!H$11*(1+$D6)-Flujo!H$19*(1+$D6)-Flujo!H$21*(1+$B6) -> 17625762 | L6: =(Flujo!I$6*(1+$B6)-Flujo!I$8*(1+$C6)-Flujo!I$11*(1+$D6))-MAX(0,(Flujo!I$6*(1+$B6)-Flujo!I$8*(1+$C6)-Flujo!I$11*(1+$D6)))*Supuestos!$B$6+Flujo!I$11*(1+$D6)-Flujo!I$19*(1+$D6)-Flujo!I$21*(1+$B6) -> 33337415 | ... N6: =(Flujo!K$6*(1+$B6)-Flujo!K$8*(1+$C6)-Flujo!K$11*(1+$D6))-MAX(0,(Flujo!K$6*(1+$B6)-Flujo!K$8*(1+$C6)-Flujo!K$11*(1+$D6)))*Supuestos!$B$6+Flujo!K$11*(1+$D6)-Flujo!K$19*(1+$D6)-Flujo!K$21*(1+$B6) -> 34825409 | O6: =(Flujo!L$6*(1+$B6)-Flujo!L$8*(1+$C6)-Flujo!L$11*(1+$D6))-MAX(0,(Flujo!L$6*(1+$B6)-Flujo!L$8*(1+$C6)-Flujo!L$11*(1+$D6)))*Supuestos!$B$6+Flujo!L$11*(1+$D6)-Flujo!L$19*(1+$D6)-Flujo!L$21*(1+$B6)+Flujo!L$22*IF(Supuestos!$B$31="valor_libro",1+$D6,1) -> 73100831 | P6: =E6+NPV(Supuestos!$B$4,F6:O6) -> -20359573
A7: ingresos -10% | B7: -0.1 | C7: 0 | D7: 0 | E7: =(Flujo!B$6*(1+$B7)-Flujo!B$8*(1+$C7)-Flujo!B$11*(1+$D7))-MAX(0,(Flujo!B$6*(1+$B7)-Flujo!B$8*(1+$C7)-Flujo!B$11*(1+$D7)))*Supuestos!$B$6+Flujo!B$11*(1+$D7)-Flujo!B$19*(1+$D7)-Flujo!B$21*(1+$B7) -> -222160000 | F7: =(Flujo!C$6*(1+$B7)-Flujo!C$8*(1+$C7)-Flujo!C$11*(1+$D7))-MAX(0,(Flujo!C$6*(1+$B7)-Flujo!C$8*(1+$C7)-Flujo!C$11*(1+$D7)))*Supuestos!$B$6+Flujo!C$11*(1+$D7)-Flujo!C$19*(1+$D7)-Flujo!C$21*(1+$B7) -> 32864300 | G7: =(Flujo!D$6*(1+$B7)-Flujo!D$8*(1+$C7)-Flujo!D$11*(1+$D7))-MAX(0,(Flujo!D$6*(1+$B7)-Flujo!D$8*(1+$C7)-Flujo!D$11*(1+$D7)))*Supuestos!$B$6+Flujo!D$11*(1+$D7)-Flujo!D$19*(1+$D7)-Flujo!D$21*(1+$B7) -> 33569969 | H7: =(Flujo!E$6*(1+$B7)-Flujo!E$8*(1+$C7)-Flujo!E$11*(1+$D7))-MAX(0,(Flujo!E$6*(1+$B7)-Flujo!E$8*(1+$C7)-Flujo!E$11*(1+$D7)))*Supuestos!$B$6+Flujo!E$11*(1+$D7)-Flujo!E$19*(1+$D7)-Flujo!E$21*(1+$B7) -> 34296808 | I7: =(Flujo!F$6*(1+$B7)-Flujo!F$8*(1+$C7)-Flujo!F$11*(1+$D7))-MAX(0,(Flujo!F$6*(1+$B7)-Flujo!F$8*(1+$C7)-Flujo!F$11*(1+$D7)))*Supuestos!$B$6+Flujo!F$11*(1+$D7)-Flujo!F$19*(1+$D7)-Flujo!F$21*(1+$B7) -> 35045452 | J7: =(Flujo!G$6*(1+$B7)-Flujo!G$8*(1+$C7)-Flujo!G$11*(1+$D7))-MAX(0,(Flujo!G$6*(1+$B7)-Flujo!G$8*(1+$C7)-Flujo!G$11*(1+$D7)))*Supuestos!$B$6+Flujo!G$11*(1+$D7)-Flujo!G$19*(1+$D7)-Flujo!G$21*(1+$B7) -> 35816556 | K7: =(Flujo!H$6*(1+$B7)-Flujo!H$8*(1+$C7)-Flujo!H$11*(1+$D7))-MAX(0,(Flujo!H$6*(1+$B7)-Flujo!H$8*(1+$C7)-Flujo!H$11*(1+$D7)))*Supuestos!$B$6+Flujo!H$11*(1+$D7)-Flujo!H$19*(1+$D7)-Flujo!H$21*(1+$B7) -> 21610793 | L7: =(Flujo!I$6*(1+$B7)-Flujo!I$8*(1+$C7)-Flujo!I$11*(1+$D7))-MAX(0,(Flujo!I$6*(1+$B7)-Flujo!I$8*(1+$C7)-Flujo!I$11*(1+$D7)))*Supuestos!$B$6+Flujo!I$11*(1+$D7)-Flujo!I$19*(1+$D7)-Flujo!I$21*(1+$B7) -> 37428856 | ... N7: =(Flujo!K$6*(1+$B7)-Flujo!K$8*(1+$C7)-Flujo!K$11*(1+$D7))-MAX(0,(Flujo!K$6*(1+$B7)-Flujo!K$8*(1+$C7)-Flujo!K$11*(1+$D7)))*Supuestos!$B$6+Flujo!K$11*(1+$D7)-Flujo!K$19*(1+$D7)-Flujo!K$21*(1+$B7) -> 39139346 | O7: =(Flujo!L$6*(1+$B7)-Flujo!L$8*(1+$C7)-Flujo!L$11*(1+$D7))-MAX(0,(Flujo!L$6*(1+$B7)-Flujo!L$8*(1+$C7)-Flujo!L$11*(1+$D7)))*Supuestos!$B$6+Flujo!L$11*(1+$D7)-Flujo!L$19*(1+$D7)-Flujo!L$21*(1+$B7)+Flujo!L$22*IF(Supuestos!$B$31="valor_libro",1+$D7,1) -> 77843268 | P7: =E7+NPV(Supuestos!$B$4,F7:O7) -> 3274313.7
A8: ingresos +10% | B8: 0.1 | C8: 0 | D8: 0 | E8: =(Flujo!B$6*(1+$B8)-Flujo!B$8*(1+$C8)-Flujo!B$11*(1+$D8))-MAX(0,(Flujo!B$6*(1+$B8)-Flujo!B$8*(1+$C8)-Flujo!B$11*(1+$D8)))*Supuestos!$B$6+Flujo!B$11*(1+$D8)-Flujo!B$19*(1+$D8)-Flujo!B$21*(1+$B8) -> -222640000 | F8: =(Flujo!C$6*(1+$B8)-Flujo!C$8*(1+$C8)-Flujo!C$11*(1+$D8))-MAX(0,(Flujo!C$6*(1+$B8)-Flujo!C$8*(1+$C8)-Flujo!C$11*(1+$D8)))*Supuestos!$B$6+Flujo!C$11*(1+$D8)-Flujo!C$19*(1+$D8)-Flujo!C$21*(1+$B8) -> 39859700 | G8: =(Flujo!D$6*(1+$B8)-Flujo!D$8*(1+$C8)-Flujo!D$11*(1+$D8))-MAX(0,(Flujo!D$6*(1+$B8)-Flujo!D$8*(1+$C8)-Flujo!D$11*(1+$D8)))*Supuestos!$B$6+Flujo!D$11*(1+$D8)-Flujo!D$19*(1+$D8)-Flujo!D$21*(1+$B8) -> 40748951 | H8: =(Flujo!E$6*(1+$B8)-Flujo!E$8*(1+$C8)-Flujo!E$11*(1+$D8))-MAX(0,(Flujo!E$6*(1+$B8)-Flujo!E$8*(1+$C8)-Flujo!E$11*(1+$D8)))*Supuestos!$B$6+Flujo!E$11*(1+$D8)-Flujo!E$19*(1+$D8)-Flujo!E$21*(1+$B8) -> 41664880 | I8: =(Flujo!F$6*(1+$B8)-Flujo!F$8*(1+$C8)-Flujo!F$11*(1+$D8))-MAX(0,(Flujo!F$6*(1+$B8)-Flujo!F$8*(1+$C8)-Flujo!F$11*(1+$D8)))*Supuestos!$B$6+Flujo!F$11*(1+$D8)-Flujo!F$19*(1+$D8)-Flujo!F$21*(1+$B8) -> 42608286 | J8: =(Flujo!G$6*(1+$B8)-Flujo!G$8*(1+$C8)-Flujo!G$11*(1+$D8))-MAX(0,(Flujo!G$6*(1+$B8)-Flujo!G$8*(1+$C8)-Flujo!G$11*(1+$D8)))*Supuestos!$B$6+Flujo!G$11*(1+$D8)-Flujo!G$19*(1+$D8)-Flujo!G$21*(1+$B8) -> 43579994 | K8: =(Flujo!H$6*(1+$B8)-Flujo!H$8*(1+$C8)-Flujo!H$11*(1+$D8))-MAX(0,(Flujo!H$6*(1+$B8)-Flujo!H$8*(1+$C8)-Flujo!H$11*(1+$D8)))*Supuestos!$B$6+Flujo!H$11*(1+$D8)-Flujo!H$19*(1+$D8)-Flujo!H$21*(1+$B8) -> 29580854 | L8: =(Flujo!I$6*(1+$B8)-Flujo!I$8*(1+$C8)-Flujo!I$11*(1+$D8))-MAX(0,(Flujo!I$6*(1+$B8)-Flujo!I$8*(1+$C8)-Flujo!I$11*(1+$D8)))*Supuestos!$B$6+Flujo!I$11*(1+$D8)-Flujo!I$19*(1+$D8)-Flujo!I$21*(1+$B8) -> 45611740 | ... N8: =(Flujo!K$6*(1+$B8)-Flujo!K$8*(1+$C8)-Flujo!K$11*(1+$D8))-MAX(0,(Flujo!K$6*(1+$B8)-Flujo!K$8*(1+$C8)-Flujo!K$11*(1+$D8)))*Supuestos!$B$6+Flujo!K$11*(1+$D8)-Flujo!K$19*(1+$D8)-Flujo!K$21*(1+$B8) -> 47767219 | O8: =(Flujo!L$6*(1+$B8)-Flujo!L$8*(1+$C8)-Flujo!L$11*(1+$D8))-MAX(0,(Flujo!L$6*(1+$B8)-Flujo!L$8*(1+$C8)-Flujo!L$11*(1+$D8)))*Supuestos!$B$6+Flujo!L$11*(1+$D8)-Flujo!L$19*(1+$D8)-Flujo!L$21*(1+$B8)+Flujo!L$22*IF(Supuestos!$B$31="valor_libro",1+$D8,1) -> 87328142 | P8: =E8+NPV(Supuestos!$B$4,F8:O8) -> 50542086
A9: ingresos +20% | B9: 0.2 | C9: 0 | D9: 0 | E9: =(Flujo!B$6*(1+$B9)-Flujo!B$8*(1+$C9)-Flujo!B$11*(1+$D9))-MAX(0,(Flujo!B$6*(1+$B9)-Flujo!B$8*(1+$C9)-Flujo!B$11*(1+$D9)))*Supuestos!$B$6+Flujo!B$11*(1+$D9)-Flujo!B$19*(1+$D9)-Flujo!B$21*(1+$B9) -> -222880000 | F9: =(Flujo!C$6*(1+$B9)-Flujo!C$8*(1+$C9)-Flujo!C$11*(1+$D9))-MAX(0,(Flujo!C$6*(1+$B9)-Flujo!C$8*(1+$C9)-Flujo!C$11*(1+$D9)))*Supuestos!$B$6+Flujo!C$11*(1+$D9)-Flujo!C$19*(1+$D9)-Flujo!C$21*(1+$B9) -> 43357400 | G9: =(Flujo!D$6*(1+$B9)-Flujo!D$8*(1+$C9)-Flujo!D$11*(1+$D9))-MAX(0,(Flujo!D$6*(1+$B9)-Flujo!D$8*(1+$C9)-Flujo!D$11*(1+$D9)))*Supuestos!$B$6+Flujo!D$11*(1+$D9)-Flujo!D$19*(1+$D9)-Flujo!D$21*(1+$B9) -> 44338442 | H9: =(Flujo!E$6*(1+$B9)-Flujo!E$8*(1+$C9)-Flujo!E$11*(1+$D9))-MAX(0,(Flujo!E$6*(1+$B9)-Flujo!E$8*(1+$C9)-Flujo!E$11*(1+$D9)))*Supuestos!$B$6+Flujo!E$11*(1+$D9)-Flujo!E$19*(1+$D9)-Flujo!E$21*(1+$B9) -> 45348915 | I9: =(Flujo!F$6*(1+$B9)-Flujo!F$8*(1+$C9)-Flujo!F$11*(1+$D9))-MAX(0,(Flujo!F$6*(1+$B9)-Flujo!F$8*(1+$C9)-Flujo!F$11*(1+$D9)))*Supuestos!$B$6+Flujo!F$11*(1+$D9)-Flujo!F$19*(1+$D9)-Flujo!F$21*(1+$B9) -> 46389703 | J9: =(Flujo!G$6*(1+$B9)-Flujo!G$8*(1+$C9)-Flujo!G$11*(1+$D9))-MAX(0,(Flujo!G$6*(1+$B9)-Flujo!G$8*(1+$C9)-Flujo!G$11*(1+$D9)))*Supuestos!$B$6+Flujo!G$11*(1+$D9)-Flujo!G$19*(1+$D9)-Flujo!G$21*(1+$B9) -> 47461714 | K9: =(Flujo!H$6*(1+$B9)-Flujo!H$8*(1+$C9)-Flujo!H$11*(1+$D9))-MAX(0,(Flujo!H$6*(1+$B9)-Flujo!H$8*(1+$C9)-Flujo!H$11*(1+$D9)))*Supuestos!$B$6+Flujo!H$11*(1+$D9)-Flujo!H$19*(1+$D9)-Flujo!H$21*(1+$B9) -> 33565885 | L9: =(Flujo!I$6*(1+$B9)-Flujo!I$8*(1+$C9)-Flujo!I$11*(1+$D9))-MAX(0,(Flujo!I$6*(1+$B9)-Flujo!I$8*(1+$C9)-Flujo!I$11*(1+$D9)))*Supuestos!$B$6+Flujo!I$11*(1+$D9)-Flujo!I$19*(1+$D9)-Flujo!I$21*(1+$B9) -> 49703182 | ... N9: =(Flujo!K$6*(1+$B9)-Flujo!K$8*(1+$C9)-Flujo!K$11*(1+$D9))-MAX(0,(Flujo!K$6*(1+$B9)-Flujo!K$8*(1+$C9)-Flujo!K$11*(1+$D9)))*Supuestos!$B$6+Flujo!K$11*(1+$D9)-Flujo!K$19*(1+$D9)-Flujo!K$21*(1+$B9) -> 52081155 | O9: =(Flujo!L$6*(1+$B9)-Flujo!L$8*(1+$C9)-Flujo!L$11*(1+$D9))-MAX(0,(Flujo!L$6*(1+$B9)-Flujo!L$8*(1+$C9)-Flujo!L$11*(1+$D9)))*Supuestos!$B$6+Flujo!L$11*(1+$D9)-Flujo!L$19*(1+$D9)-Flujo!L$21*(1+$B9)+Flujo!L$22*IF(Supuestos!$B$31="valor_libro",1+$D9,1) -> 92070579 | P9: =E9+NPV(Supuestos!$B$4,F9:O9) -> 74175972
A10: costos -20% | B10: 0 | C10: -0.2 | D10: 0 | E10: =(Flujo!B$6*(1+$B10)-Flujo!B$8*(1+$C10)-Flujo!B$11*(1+$D10))-MAX(0,(Flujo!B$6*(1+$B10)-Flujo!B$8*(1+$C10)-Flujo!B$11*(1+$D10)))*Supuestos!$B$6+Flujo!B$11*(1+$D10)-Flujo!B$19*(1+$D10)-Flujo!B$21*(1+$B10) -> -222400000 | F10: =(Flujo!C$6*(1+$B10)-Flujo!C$8*(1+$C10)-Flujo!C$11*(1+$D10))-MAX(0,(Flujo!C$6*(1+$B10)-Flujo!C$8*(1+$C10)-Flujo!C$11*(1+$D10)))*Supuestos!$B$6+Flujo!C$11*(1+$D10)-Flujo!C$19*(1+$D10)-Flujo!C$21*(1+$B10) -> 37165000 | G10: =(Flujo!D$6*(1+$B10)-Flujo!D$8*(1+$C10)-Flujo!D$11*(1+$D10))-MAX(0,(Flujo!D$6*(1+$B10)-Flujo!D$8*(1+$C10)-Flujo!D$11*(1+$D10)))*Supuestos!$B$6+Flujo!D$11*(1+$D10)-Flujo!D$19*(1+$D10)-Flujo!D$21*(1+$B10) -> 37986550 | H10: =(Flujo!E$6*(1+$B10)-Flujo!E$8*(1+$C10)-Flujo!E$11*(1+$D10))-MAX(0,(Flujo!E$6*(1+$B10)-Flujo!E$8*(1+$C10)-Flujo!E$11*(1+$D10)))*Supuestos!$B$6+Flujo!E$11*(1+$D10)-Flujo!E$19*(1+$D10)-Flujo!E$21*(1+$B10) -> 38832746 | I10: =(Flujo!F$6*(1+$B10)-Flujo!F$8*(1+$C10)-Flujo!F$11*(1+$D10))-MAX(0,(Flujo!F$6*(1+$B10)-Flujo!F$8*(1+$C10)-Flujo!F$11*(1+$D10)))*Supuestos!$B$6+Flujo!F$11*(1+$D10)-Flujo!F$19*(1+$D10)-Flujo!F$21*(1+$B10) -> 39704329 | J10: =(Flujo!G$6*(1+$B10)-Flujo!G$8*(1+$C10)-Flujo!G$11*(1+$D10))-MAX(0,(Flujo!G$6*(1+$B10)-Flujo!G$8*(1+$C10)-Flujo!G$11*(1+$D10)))*Supuestos!$B$6+Flujo!G$11*(1+$D10)-Flujo!G$19*(1+$D10)-Flujo!G$21*(1+$B10) -> 40602059 | K10: =(Flujo!H$6*(1+$B10)-Flujo!H$8*(1+$C10)-Flujo!H$11*(1+$D10))-MAX(0,(Flujo!H$6*(1+$B10)-Flujo!H$8*(1+$C10)-Flujo!H$11*(1+$D10)))*Supuestos!$B$6+Flujo!H$11*(1+$D10)-Flujo!H$19*(1+$D10)-Flujo!H$21*(1+$B10) -> 26526721 | L10: =(Flujo!I$6*(1+$B10)-Flujo!I$8*(1+$C10)-Flujo!I$11*(1+$D10))-MAX(0,(Flujo!I$6*(1+$B10)-Flujo!I$8*(1+$C10)-Flujo!I$11*(1+$D10)))*Supuestos!$B$6+Flujo!I$11*(1+$D10)-Flujo!I$19*(1+$D10)-Flujo!I$21*(1+$B10) -> 42479122 | ... N10: =(Flujo!K$6*(1+$B10)-Flujo!K$8*(1+$C10)-Flujo!K$11*(1+$D10))-MAX(0,(Flujo!K$6*(1+$B10)-Flujo!K$8*(1+$C10)-Flujo!K$11*(1+$D10)))*Supuestos!$B$6+Flujo!K$11*(1+$D10)-Flujo!K$19*(1+$D10)-Flujo!K$21*(1+$B10) -> 44470499 | O10: =(Flujo!L$6*(1+$B10)-Flujo!L$8*(1+$C10)-Flujo!L$11*(1+$D10))-MAX(0,(Flujo!L$6*(1+$B10)-Flujo!L$8*(1+$C10)-Flujo!L$11*(1+$D10)))*Supuestos!$B$6+Flujo!L$11*(1+$D10)-Flujo!L$19*(1+$D10)-Flujo!L$21*(1+$B10)+Flujo!L$22*IF(Supuestos!$B$31="valor_libro",1+$D10,1) -> 83633438 | P10: =E10+NPV(Supuestos!$B$4,F10:O10) -> 32435846
A11: costos -10% | B11: 0 | C11: -0.1 | D11: 0 | E11: =(Flujo!B$6*(1+$B11)-Flujo!B$8*(1+$C11)-Flujo!B$11*(1+$D11))-MAX(0,(Flujo!B$6*(1+$B11)-Flujo!B$8*(1+$C11)-Flujo!B$11*(1+$D11)))*Supuestos!$B$6+Flujo!B$11*(1+$D11)-Flujo!B$19*(1+$D11)-Flujo!B$21*(1+$B11) -> -222400000 | F11: =(Flujo!C$6*(1+$B11)-Flujo!C$8*(1+$C11)-Flujo!C$11*(1+$D11))-MAX(0,(Flujo!C$6*(1+$B11)-Flujo!C$8*(1+$C11)-Flujo!C$11*(1+$D11)))*Supuestos!$B$6+Flujo!C$11*(1+$D11)-Flujo!C$19*(1+$D11)-Flujo!C$21*(1+$B11) -> 36763500 | G11: =(Flujo!D$6*(1+$B11)-Flujo!D$8*(1+$C11)-Flujo!D$11*(1+$D11))-MAX(0,(Flujo!D$6*(1+$B11)-Flujo!D$8*(1+$C11)-Flujo!D$11*(1+$D11)))*Supuestos!$B$6+Flujo!D$11*(1+$D11)-Flujo!D$19*(1+$D11)-Flujo!D$21*(1+$B11) -> 37573005 | H11: =(Flujo!E$6*(1+$B11)-Flujo!E$8*(1+$C11)-Flujo!E$11*(1+$D11))-MAX(0,(Flujo!E$6*(1+$B11)-Flujo!E$8*(1+$C11)-Flujo!E$11*(1+$D11)))*Supuestos!$B$6+Flujo!E$11*(1+$D11)-Flujo!E$19*(1+$D11)-Flujo!E$21*(1+$B11) -> 38406795 | I11: =(Flujo!F$6*(1+$B11)-Flujo!F$8*(1+$C11)-Flujo!F$11*(1+$D11))-MAX(0,(Flujo!F$6*(1+$B11)-Flujo!F$8*(1+$C11)-Flujo!F$11*(1+$D11)))*Supuestos!$B$6+Flujo!F$11*(1+$D11)-Flujo!F$19*(1+$D11)-Flujo!F$21*(1+$B11) -> 39265599 | J11: =(Flujo!G$6*(1+$B11)-Flujo!G$8*(1+$C11)-Flujo!G$11*(1+$D11))-MAX(0,(Flujo!G$6*(1+$B11)-Flujo!G$8*(1+$C11)-Flujo!G$11*(1+$D11)))*Supuestos!$B$6+Flujo!G$11*(1+$D11)-Flujo!G$19*(1+$D11)-Flujo!G$21*(1+$B11) -> 40150167 | K11: =(Flujo!H$6*(1+$B11)-Flujo!H$8*(1+$C11)-Flujo!H$11*(1+$D11))-MAX(0,(Flujo!H$6*(1+$B11)-Flujo!H$8*(1+$C11)-Flujo!H$11*(1+$D11)))*Supuestos!$B$6+Flujo!H$11*(1+$D11)-Flujo!H$19*(1+$D11)-Flujo!H$21*(1+$B11) -> 26061272 | L11: =(Flujo!I$6*(1+$B11)-Flujo!I$8*(1+$C11)-Flujo!I$11*(1+$D11))-MAX(0,(Flujo!I$6*(1+$B11)-Flujo!I$8*(1+$C11)-Flujo!I$11*(1+$D11)))*Supuestos!$B$6+Flujo!I$11*(1+$D11)-Flujo!I$19*(1+$D11)-Flujo!I$21*(1+$B11) -> 41999710 | ... N11: =(Flujo!K$6*(1+$B11)-Flujo!K$8*(1+$C11)-Flujo!K$11*(1+$D11))-MAX(0,(Flujo!K$6*(1+$B11)-Flujo!K$8*(1+$C11)-Flujo!K$11*(1+$D11)))*Supuestos!$B$6+Flujo!K$11*(1+$D11)-Flujo!K$19*(1+$D11)-Flujo!K$21*(1+$B11) -> 43961890 | O11: =(Flujo!L$6*(1+$B11)-Flujo!L$8*(1+$C11)-Flujo!L$11*(1+$D11))-MAX(0,(Flujo!L$6*(1+$B11)-Flujo!L$8*(1+$C11)-Flujo!L$11*(1+$D11)))*Supuestos!$B$6+Flujo!L$11*(1+$D11)-Flujo!L$19*(1+$D11)-Flujo!L$21*(1+$B11)+Flujo!L$22*IF(Supuestos!$B$31="valor_libro",1+$D11,1) -> 83109572 | P11: =E11+NPV(Supuestos!$B$4,F11:O11) -> 29672023
A12: costos +10% | B12: 0 | C12: 0.1 | D12: 0 | E12: =(Flujo!B$6*(1+$B12)-Flujo!B$8*(1+$C12)-Flujo!B$11*(1+$D12))-MAX(0,(Flujo!B$6*(1+$B12)-Flujo!B$8*(1+$C12)-Flujo!B$11*(1+$D12)))*Supuestos!$B$6+Flujo!B$11*(1+$D12)-Flujo!B$19*(1+$D12)-Flujo!B$21*(1+$B12) -> -222400000 | F12: =(Flujo!C$6*(1+$B12)-Flujo!C$8*(1+$C12)-Flujo!C$11*(1+$D12))-MAX(0,(Flujo!C$6*(1+$B12)-Flujo!C$8*(1+$C12)-Flujo!C$11*(1+$D12)))*Supuestos!$B$6+Flujo!C$11*(1+$D12)-Flujo!C$19*(1+$D12)-Flujo!C$21*(1+$B12) -> 35960500 | G12: =(Flujo!D$6*(1+$B12)-Flujo!D$8*(1+$C12)-Flujo!D$11*(1+$D12))-MAX(0,(Flujo!D$6*(1+$B12)-Flujo!D$8*(1+$C12)-Flujo!D$11*(1+$D12)))*Supuestos!$B$6+Flujo!D$11*(1+$D12)-Flujo!D$19*(1+$D12)-Flujo!D$21*(1+$B12) -> 36745915 | H12: =(Flujo!E$6*(1+$B12)-Flujo!E$8*(1+$C12)-Flujo!E$11*(1+$D12))-MAX(0,(Flujo!E$6*(1+$B12)-Flujo!E$8*(1+$C12)-Flujo!E$11*(1+$D12)))*Supuestos!$B$6+Flujo!E$11*(1+$D12)-Flujo!E$19*(1+$D12)-Flujo!E$21*(1+$B12) -> 37554892 | I12: =(Flujo!F$6*(1+$B12)-Flujo!F$8*(1+$C12)-Flujo!F$11*(1+$D12))-MAX(0,(Flujo!F$6*(1+$B12)-Flujo!F$8*(1+$C12)-Flujo!F$11*(1+$D12)))*Supuestos!$B$6+Flujo!F$11*(1+$D12)-Flujo!F$19*(1+$D12)-Flujo!F$21*(1+$B12) -> 38388139 | J12: =(Flujo!G$6*(1+$B12)-Flujo!G$8*(1+$C12)-Flujo!G$11*(1+$D12))-MAX(0,(Flujo!G$6*(1+$B12)-Flujo!G$8*(1+$C12)-Flujo!G$11*(1+$D12)))*Supuestos!$B$6+Flujo!G$11*(1+$D12)-Flujo!G$19*(1+$D12)-Flujo!G$21*(1+$B12) -> 39246383 | K12: =(Flujo!H$6*(1+$B12)-Flujo!H$8*(1+$C12)-Flujo!H$11*(1+$D12))-MAX(0,(Flujo!H$6*(1+$B12)-Flujo!H$8*(1+$C12)-Flujo!H$11*(1+$D12)))*Supuestos!$B$6+Flujo!H$11*(1+$D12)-Flujo!H$19*(1+$D12)-Flujo!H$21*(1+$B12) -> 25130375 | L12: =(Flujo!I$6*(1+$B12)-Flujo!I$8*(1+$C12)-Flujo!I$11*(1+$D12))-MAX(0,(Flujo!I$6*(1+$B12)-Flujo!I$8*(1+$C12)-Flujo!I$11*(1+$D12)))*Supuestos!$B$6+Flujo!I$11*(1+$D12)-Flujo!I$19*(1+$D12)-Flujo!I$21*(1+$B12) -> 41040886 | ... N12: =(Flujo!K$6*(1+$B12)-Flujo!K$8*(1+$C12)-Flujo!K$11*(1+$D12))-MAX(0,(Flujo!K$6*(1+$B12)-Flujo!K$8*(1+$C12)-Flujo!K$11*(1+$D12)))*Supuestos!$B$6+Flujo!K$11*(1+$D12)-Flujo!K$19*(1+$D12)-Flujo!K$21*(1+$B12) -> 42944674 | O12: =(Flujo!L$6*(1+$B12)-Flujo!L$8*(1+$C12)-Flujo!L$11*(1+$D12))-MAX(0,(Flujo!L$6*(1+$B12)-Flujo!L$8*(1+$C12)-Flujo!L$11*(1+$D12)))*Supuestos!$B$6+Flujo!L$11*(1+$D12)-Flujo!L$19*(1+$D12)-Flujo!L$21*(1+$B12)+Flujo!L$22*IF(Supuestos!$B$31="valor_libro",1+$D12,1) -> 82061839 | P12: =E12+NPV(Supuestos!$B$4,F12:O12) -> 24144377
A13: costos +20% | B13: 0 | C13: 0.2 | D13: 0 | E13: =(Flujo!B$6*(1+$B13)-Flujo!B$8*(1+$C13)-Flujo!B$11*(1+$D13))-MAX(0,(Flujo!B$6*(1+$B13)-Flujo!B$8*(1+$C13)-Flujo!B$11*(1+$D13)))*Supuestos!$B$6+Flujo!B$11*(1+$D13)-Flujo!B$19*(1+$D13)-Flujo!B$21*(1+$B13) -> -222400000 | F13: =(Flujo!C$6*(1+$B13)-Flujo!C$8*(1+$C13)-Flujo!C$11*(1+$D13))-MAX(0,(Flujo!C$6*(1+$B13)-Flujo!C$8*(1+$C13)-Flujo!C$11*(1+$D13)))*Supuestos!$B$6+Flujo!C$11*(1+$D13)-Flujo!C$19*(1+$D13)-Flujo!C$21*(1+$B13) -> 35559000 | G13: =(Flujo!D$6*(1+$B13)-Flujo!D$8*(1+$C13)-Flujo!D$11*(1+$D13))-MAX(0,(Flujo!D$6*(1+$B13)-Flujo!D$8*(1+$C13)-Flujo!D$11*(1+$D13)))*Supuestos!$B$6+Flujo!D$11*(1+$D13)-Flujo!D$19*(1+$D13)-Flujo!D$21*(1+$B13) -> 36332370 | H13: =(Flujo!E$6*(1+$B13)-Flujo!E$8*(1+$C13)-Flujo!E$11*(1+$D13))-MAX(0,(Flujo!E$6*(1+$B13)-Flujo!E$8*(1+$C13)-Flujo!E$11*(1+$D13)))*Supuestos!$B$6+Flujo!E$11*(1+$D13)-Flujo!E$19*(1+$D13)-Flujo!E$21*(1+$B13) -> 37128941 | I13: =(Flujo!F$6*(1+$B13)-Flujo!F$8*(1+$C13)-Flujo!F$11*(1+$D13))-MAX(0,(Flujo!F$6*(1+$B13)-Flujo!F$8*(1+$C13)-Flujo!F$11*(1+$D13)))*Supuestos!$B$6+Flujo!F$11*(1+$D13)-Flujo!F$19*(1+$D13)-Flujo!F$21*(1+$B13) -> 37949409 | J13: =(Flujo!G$6*(1+$B13)-Flujo!G$8*(1+$C13)-Flujo!G$11*(1+$D13))-MAX(0,(Flujo!G$6*(1+$B13)-Flujo!G$8*(1+$C13)-Flujo!G$11*(1+$D13)))*Supuestos!$B$6+Flujo!G$11*(1+$D13)-Flujo!G$19*(1+$D13)-Flujo!G$21*(1+$B13) -> 38794492 | K13: =(Flujo!H$6*(1+$B13)-Flujo!H$8*(1+$C13)-Flujo!H$11*(1+$D13))-MAX(0,(Flujo!H$6*(1+$B13)-Flujo!H$8*(1+$C13)-Flujo!H$11*(1+$D13)))*Supuestos!$B$6+Flujo!H$11*(1+$D13)-Flujo!H$19*(1+$D13)-Flujo!H$21*(1+$B13) -> 24664926 | L13: =(Flujo!I$6*(1+$B13)-Flujo!I$8*(1+$C13)-Flujo!I$11*(1+$D13))-MAX(0,(Flujo!I$6*(1+$B13)-Flujo!I$8*(1+$C13)-Flujo!I$11*(1+$D13)))*Supuestos!$B$6+Flujo!I$11*(1+$D13)-Flujo!I$19*(1+$D13)-Flujo!I$21*(1+$B13) -> 40561474 | ... N13: =(Flujo!K$6*(1+$B13)-Flujo!K$8*(1+$C13)-Flujo!K$11*(1+$D13))-MAX(0,(Flujo!K$6*(1+$B13)-Flujo!K$8*(1+$C13)-Flujo!K$11*(1+$D13)))*Supuestos!$B$6+Flujo!K$11*(1+$D13)-Flujo!K$19*(1+$D13)-Flujo!K$21*(1+$B13) -> 42436066 | O13: =(Flujo!L$6*(1+$B13)-Flujo!L$8*(1+$C13)-Flujo!L$11*(1+$D13))-MAX(0,(Flujo!L$6*(1+$B13)-Flujo!L$8*(1+$C13)-Flujo!L$11*(1+$D13)))*Supuestos!$B$6+Flujo!L$11*(1+$D13)-Flujo!L$19*(1+$D13)-Flujo!L$21*(1+$B13)+Flujo!L$22*IF(Supuestos!$B$31="valor_libro",1+$D13,1) -> 81537972 | P13: =E13+NPV(Supuestos!$B$4,F13:O13) -> 21380554
A14: inversion -20% | B14: 0 | C14: 0 | D14: -0.2 | E14: =(Flujo!B$6*(1+$B14)-Flujo!B$8*(1+$C14)-Flujo!B$11*(1+$D14))-MAX(0,(Flujo!B$6*(1+$B14)-Flujo!B$8*(1+$C14)-Flujo!B$11*(1+$D14)))*Supuestos!$B$6+Flujo!B$11*(1+$D14)-Flujo!B$19*(1+$D14)-Flujo!B$21*(1+$B14) -> -178400000 | F14: =(Flujo!C$6*(1+$B14)-Flujo!C$8*(1+$C14)-Flujo!C$11*(1+$D14))-MAX(0,(Flujo!C$6*(1+$B14)-Flujo!C$8*(1+$C14)-Flujo!C$11*(1+$D14)))*Supuestos!$B$6+Flujo!C$11*(1+$D14)-Flujo!C$19*(1+$D14)-Flujo!C$21*(1+$B14) -> 35282000 | G14: =(Flujo!D$6*(1+$B14)-Flujo!D$8*(1+$C14)-Flujo!D$11*(1+$D14))-MAX(0,(Flujo!D$6*(1+$B14)-Flujo!D$8*(1+$C14)-Flujo!D$11*(1+$D14)))*Supuestos!$B$6+Flujo!D$11*(1+$D14)-Flujo!D$19*(1+$D14)-Flujo!D$21*(1+$B14) -> 36079460 | H14: =(Flujo!E$6*(1+$B14)-Flujo!E$8*(1+$C14)-Flujo!E$11*(1+$D14))-MAX(0,(Flujo!E$6*(1+$B14)-Flujo!E$8*(1+$C14)-Flujo!E$11*(1+$D14)))*Supuestos!$B$6+Flujo!E$11*(1+$D14)-Flujo!E$19*(1+$D14)-Flujo!E$21*(1+$B14) -> 36900844 | I14: =(Flujo!F$6*(1+$B14)-Flujo!F$8*(1+$C14)-Flujo!F$11*(1+$D14))-MAX(0,(Flujo!F$6*(1+$B14)-Flujo!F$8*(1+$C14)-Flujo!F$11*(1+$D14)))*Supuestos!$B$6+Flujo!F$11*(1+$D14)-Flujo!F$19*(1+$D14)-Flujo!F$21*(1+$B14) -> 37746869 | J14: =(Flujo!G$6*(1+$B14)-Flujo!G$8*(1+$C14)-Flujo!G$11*(1+$D14))-MAX(0,(Flujo!G$6*(1+$B14)-Flujo!G$8*(1+$C14)-Flujo!G$11*(1+$D14)))*Supuestos!$B$6+Flujo!G$11*(1+$D14)-Flujo!G$19*(1+$D14)-Flujo!G$21*(1+$B14) -> 38618275 | K14: =(Flujo!H$6*(1+$B14)-Flujo!H$8*(1+$C14)-Flujo!H$11*(1+$D14))-MAX(0,(Flujo!H$6*(1+$B14)-Flujo!H$8*(1+$C14)-Flujo!H$11*(1+$D14)))*Supuestos!$B$6+Flujo!H$11*(1+$D14)-Flujo!H$19*(1+$D14)-Flujo!H$21*(1+$B14) -> 27515823 | L14: =(Flujo!I$6*(1+$B14)-Flujo!I$8*(1+$C14)-Flujo!I$11*(1+$D14))-MAX(0,(Flujo!I$6*(1+$B14)-Flujo!I$8*(1+$C14)-Flujo!I$11*(1+$D14)))*Supuestos!$B$6+Flujo!I$11*(1+$D14)-Flujo!I$19*(1+$D14)-Flujo!I$21*(1+$B14) -> 40440298 | ... N14: =(Flujo!K$6*(1+$B14)-Flujo!K$8*(1+$C14)-Flujo!K$11*(1+$D14))-MAX(0,(Flujo!K$6*(1+$B14)-Flujo!K$8*(1+$C14)-Flujo!K$11*(1+$D14)))*Supuestos!$B$6+Flujo!K$11*(1+$D14)-Flujo!K$19*(1+$D14)-Flujo!K$21*(1+$B14) -> 42373282 | O14: =(Flujo!L$6*(1+$B14)-Flujo!L$8*(1+$C14)-Flujo!L$11*(1+$D14))-MAX(0,(Flujo!L$6*(1+$B14)-Flujo!L$8*(1+$C14)-Flujo!L$11*(1+$D14)))*Supuestos!$B$6+Flujo!L$11*(1+$D14)-Flujo!L$19*(1+$D14)-Flujo!L$21*(1+$B14)+Flujo!L$22*IF(Supuestos!$B$31="valor_libro",1+$D14,1) -> 74505705 | P14: =E14+NPV(Supuestos!$B$4,F14:O14) -> 63266686
A15: inversion -10% | B15: 0 | C15: 0 | D15: -0.1 | E15: =(Flujo!B$6*(1+$B15)-Flujo!B$8*(1+$C15)-Flujo!B$11*(1+$D15))-MAX(0,(Flujo!B$6*(1+$B15)-Flujo!B$8*(1+$C15)-Flujo!B$11*(1+$D15)))*Supuestos!$B$6+Flujo!B$11*(1+$D15)-Flujo!B$19*(1+$D15)-Flujo!B$21*(1+$B15) -> -200400000 | F15: =(Flujo!C$6*(1+$B15)-Flujo!C$8*(1+$C15)-Flujo!C$11*(1+$D15))-MAX(0,(Flujo!C$6*(1+$B15)-Flujo!C$8*(1+$C15)-Flujo!C$11*(1+$D15)))*Supuestos!$B$6+Flujo!C$11*(1+$D15)-Flujo!C$19*(1+$D15)-Flujo!C$21*(1+$B15) -> 35822000 | G15: =(Flujo!D$6*(1+$B15)-Flujo!D$8*(1+$C15)-Flujo!D$11*(1+$D15))-MAX(0,(Flujo!D$6*(1+$B15)-Flujo!D$8*(1+$C15)-Flujo!D$11*(1+$D15)))*Supuestos!$B$6+Flujo!D$11*(1+$D15)-Flujo!D$19*(1+$D15)-Flujo!D$21*(1+$B15) -> 36619460 | H15: =(Flujo!E$6*(1+$B15)-Flujo!E$8*(1+$C15)-Flujo!E$11*(1+$D15))-MAX(0,(Flujo!E$6*(1+$B15)-Flujo!E$8*(1+$C15)-Flujo!E$11*(1+$D15)))*Supuestos!$B$6+Flujo!E$11*(1+$D15)-Flujo!E$19*(1+$D15)-Flujo!E$21*(1+$B15) -> 37440844 | I15: =(Flujo!F$6*(1+$B15)-Flujo!F$8*(1+$C15)-Flujo!F$11*(1+$D15))-MAX(0,(Flujo!F$6*(1+$B15)-Flujo!F$8*(1+$C15)-Flujo!F$11*(1+$D15)))*Supuestos!$B$6+Flujo!F$11*(1+$D15)-Flujo!F$19*(1+$D15)-Flujo!F$21*(1+$B15) -> 38286869 | J15: =(Flujo!G$6*(1+$B15)-Flujo!G$8*(1+$C15)-Flujo!G$11*(1+$D15))-MAX(0,(Flujo!G$6*(1+$B15)-Flujo!G$8*(1+$C15)-Flujo!G$11*(1+$D15)))*Supuestos!$B$6+Flujo!G$11*(1+$D15)-Flujo!G$19*(1+$D15)-Flujo!G$21*(1+$B15) -> 39158275 | K15: =(Flujo!H$6*(1+$B15)-Flujo!H$8*(1+$C15)-Flujo!H$11*(1+$D15))-MAX(0,(Flujo!H$6*(1+$B15)-Flujo!H$8*(1+$C15)-Flujo!H$11*(1+$D15)))*Supuestos!$B$6+Flujo!H$11*(1+$D15)-Flujo!H$19*(1+$D15)-Flujo!H$21*(1+$B15) -> 26555823 | L15: =(Flujo!I$6*(1+$B15)-Flujo!I$8*(1+$C15)-Flujo!I$11*(1+$D15))-MAX(0,(Flujo!I$6*(1+$B15)-Flujo!I$8*(1+$C15)-Flujo!I$11*(1+$D15)))*Supuestos!$B$6+Flujo!I$11*(1+$D15)-Flujo!I$19*(1+$D15)-Flujo!I$21*(1+$B15) -> 40980298 | ... N15: =(Flujo!K$6*(1+$B15)-Flujo!K$8*(1+$C15)-Flujo!K$11*(1+$D15))-MAX(0,(Flujo!K$6*(1+$B15)-Flujo!K$8*(1+$C15)-Flujo!K$11*(1+$D15)))*Supuestos!$B$6+Flujo!K$11*(1+$D15)-Flujo!K$19*(1+$D15)-Flujo!K$21*(1+$B15) -> 42913282 | O15: =(Flujo!L$6*(1+$B15)-Flujo!L$8*(1+$C15)-Flujo!L$11*(1+$D15))-MAX(0,(Flujo!L$6*(1+$B15)-Flujo!L$8*(1+$C15)-Flujo!L$11*(1+$D15)))*Supuestos!$B$6+Flujo!L$11*(1+$D15)-Flujo!L$19*(1+$D15)-Flujo!L$21*(1+$B15)+Flujo!L$22*IF(Supuestos!$B$31="valor_libro",1+$D15,1) -> 78545705 | P15: =E15+NPV(Supuestos!$B$4,F15:O15) -> 45087443
A16: inversion +10% | B16: 0 | C16: 0 | D16: 0.1 | E16: =(Flujo!B$6*(1+$B16)-Flujo!B$8*(1+$C16)-Flujo!B$11*(1+$D16))-MAX(0,(Flujo!B$6*(1+$B16)-Flujo!B$8*(1+$C16)-Flujo!B$11*(1+$D16)))*Supuestos!$B$6+Flujo!B$11*(1+$D16)-Flujo!B$19*(1+$D16)-Flujo!B$21*(1+$B16) -> -244400000 | F16: =(Flujo!C$6*(1+$B16)-Flujo!C$8*(1+$C16)-Flujo!C$11*(1+$D16))-MAX(0,(Flujo!C$6*(1+$B16)-Flujo!C$8*(1+$C16)-Flujo!C$11*(1+$D16)))*Supuestos!$B$6+Flujo!C$11*(1+$D16)-Flujo!C$19*(1+$D16)-Flujo!C$21*(1+$B16) -> 36902000 | G16: =(Flujo!D$6*(1+$B16)-Flujo!D$8*(1+$C16)-Flujo!D$11*(1+$D16))-MAX(0,(Flujo!D$6*(1+$B16)-Flujo!D$8*(1+$C16)-Flujo!D$11*(1+$D16)))*Supuestos!$B$6+Flujo!D$11*(1+$D16)-Flujo!D$19*(1+$D16)-Flujo!D$21*(1+$B16) -> 37699460 | H16: =(Flujo!E$6*(1+$B16)-Flujo!E$8*(1+$C16)-Flujo!E$11*(1+$D16))-MAX(0,(Flujo!E$6*(1+$B16)-Flujo!E$8*(1+$C16)-Flujo!E$11*(1+$D16)))*Supuestos!$B$6+Flujo!E$11*(1+$D16)-Flujo!E$19*(1+$D16)-Flujo!E$21*(1+$B16) -> 38520844 | I16: =(Flujo!F$6*(1+$B16)-Flujo!F$8*(1+$C16)-Flujo!F$11*(1+$D16))-MAX(0,(Flujo!F$6*(1+$B16)-Flujo!F$8*(1+$C16)-Flujo!F$11*(1+$D16)))*Supuestos!$B$6+Flujo!F$11*(1+$D16)-Flujo!F$19*(1+$D16)-Flujo!F$21*(1+$B16) -> 39366869 | J16: =(Flujo!G$6*(1+$B16)-Flujo!G$8*(1+$C16)-Flujo!G$11*(1+$D16))-MAX(0,(Flujo!G$6*(1+$B16)-Flujo!G$8*(1+$C16)-Flujo!G$11*(1+$D16)))*Supuestos!$B$6+Flujo!G$11*(1+$D16)-Flujo!G$19*(1+$D16)-Flujo!G$21*(1+$B16) -> 40238275 | K16: =(Flujo!H$6*(1+$B16)-Flujo!H$8*(1+$C16)-Flujo!H$11*(1+$D16))-MAX(0,(Flujo!H$6*(1+$B16)-Flujo!H$8*(1+$C16)-Flujo!H$11*(1+$D16)))*Supuestos!$B$6+Flujo!H$11*(1+$D16)-Flujo!H$19*(1+$D16)-Flujo!H$21*(1+$B16) -> 24635823 | L16: =(Flujo!I$6*(1+$B16)-Flujo!I$8*(1+$C16)-Flujo!I$11*(1+$D16))-MAX(0,(Flujo!I$6*(1+$B16)-Flujo!I$8*(1+$C16)-Flujo!I$11*(1+$D16)))*Supuestos!$B$6+Flujo!I$11*(1+$D16)-Flujo!I$19*(1+$D16)-Flujo!I$21*(1+$B16) -> 42060298 | ... N16: =(Flujo!K$6*(1+$B16)-Flujo!K$8*(1+$C16)-Flujo!K$11*(1+$D16))-MAX(0,(Flujo!K$6*(1+$B16)-Flujo!K$8*(1+$C16)-Flujo!K$11*(1+$D16)))*Supuestos!$B$6+Flujo!K$11*(1+$D16)-Flujo!K$19*(1+$D16)-Flujo!K$21*(1+$B16) -> 43993282 | O16: =(Flujo!L$6*(1+$B16)-Flujo!L$8*(1+$C16)-Flujo!L$11*(1+$D16))-MAX(0,(Flujo!L$6*(1+$B16)-Flujo!L$8*(1+$C16)-Flujo!L$11*(1+$D16)))*Supuestos!$B$6+Flujo!L$11*(1+$D16)-Flujo!L$19*(1+$D16)-Flujo!L$21*(1+$B16)+Flujo!L$22*IF(Supuestos!$B$31="valor_libro",1+$D16,1) -> 86625705 | P16: =E16+NPV(Supuestos!$B$4,F16:O16) -> 8728956.8
A17: inversion +20% | B17: 0 | C17: 0 | D17: 0.2 | E17: =(Flujo!B$6*(1+$B17)-Flujo!B$8*(1+$C17)-Flujo!B$11*(1+$D17))-MAX(0,(Flujo!B$6*(1+$B17)-Flujo!B$8*(1+$C17)-Flujo!B$11*(1+$D17)))*Supuestos!$B$6+Flujo!B$11*(1+$D17)-Flujo!B$19*(1+$D17)-Flujo!B$21*(1+$B17) -> -266400000 | F17: =(Flujo!C$6*(1+$B17)-Flujo!C$8*(1+$C17)-Flujo!C$11*(1+$D17))-MAX(0,(Flujo!C$6*(1+$B17)-Flujo!C$8*(1+$C17)-Flujo!C$11*(1+$D17)))*Supuestos!$B$6+Flujo!C$11*(1+$D17)-Flujo!C$19*(1+$D17)-Flujo!C$21*(1+$B17) -> 37442000 | G17: =(Flujo!D$6*(1+$B17)-Flujo!D$8*(1+$C17)-Flujo!D$11*(1+$D17))-MAX(0,(Flujo!D$6*(1+$B17)-Flujo!D$8*(1+$C17)-Flujo!D$11*(1+$D17)))*Supuestos!$B$6+Flujo!D$11*(1+$D17)-Flujo!D$19*(1+$D17)-Flujo!D$21*(1+$B17) -> 38239460 | H17: =(Flujo!E$6*(1+$B17)-Flujo!E$8*(1+$C17)-Flujo!E$11*(1+$D17))-MAX(0,(Flujo!E$6*(1+$B17)-Flujo!E$8*(1+$C17)-Flujo!E$11*(1+$D17)))*Supuestos!$B$6+Flujo!E$11*(1+$D17)-Flujo!E$19*(1+$D17)-Flujo!E$21*(1+$B17) -> 39060844 | I17: =(Flujo!F$6*(1+$B17)-Flujo!F$8*(1+$C17)-Flujo!F$11*(1+$D17))-MAX(0,(Flujo!F$6*(1+$B17)-Flujo!F$8*(1+$C17)-Flujo!F$11*(1+$D17)))*Supuestos!$B$6+Flujo!F$11*(1+$D17)-Flujo!F$19*(1+$D17)-Flujo!F$21*(1+$B17) -> 39906869 | J17: =(Flujo!G$6*(1+$B17)-Flujo!G$8*(1+$C17)-Flujo!G$11*(1+$D17))-MAX(0,(Flujo!G$6*(1+$B17)-Flujo!G$8*(1+$C17)-Flujo!G$11*(1+$D17)))*Supuestos!$B$6+Flujo!G$11*(1+$D17)-Flujo!G$19*(1+$D17)-Flujo!G$21*(1+$B17) -> 40778275 | K17: =(Flujo!H$6*(1+$B17)-Flujo!H$8*(1+$C17)-Flujo!H$11*(1+$D17))-MAX(0,(Flujo!H$6*(1+$B17)-Flujo!H$8*(1+$C17)-Flujo!H$11*(1+$D17)))*Supuestos!$B$6+Flujo!H$11*(1+$D17)-Flujo!H$19*(1+$D17)-Flujo!H$21*(1+$B17) -> 23675823 | L17: =(Flujo!I$6*(1+$B17)-Flujo!I$8*(1+$C17)-Flujo!I$11*(1+$D17))-MAX(0,(Flujo!I$6*(1+$B17)-Flujo!I$8*(1+$C17)-Flujo!I$11*(1+$D17)))*Supuestos!$B$6+Flujo!I$11*(1+$D17)-Flujo!I$19*(1+$D17)-Flujo!I$21*(1+$B17) -> 42600298 | ... N17: =(Flujo!K$6*(1+$B17)-Flujo!K$8*(1+$C17)-Flujo!K$11*(1+$D17))-MAX(0,(Flujo!K$6*(1+$B17)-Flujo!K$8*(1+$C17)-Flujo!K$11*(1+$D17)))*Supuestos!$B$6+Flujo!K$11*(1+$D17)-Flujo!K$19*(1+$D17)-Flujo!K$21*(1+$B17) -> 44533282 | O17: =(Flujo!L$6*(1+$B17)-Flujo!L$8*(1+$C17)-Flujo!L$11*(1+$D17))-MAX(0,(Flujo!L$6*(1+$B17)-Flujo!L$8*(1+$C17)-Flujo!L$11*(1+$D17)))*Supuestos!$B$6+Flujo!L$11*(1+$D17)-Flujo!L$19*(1+$D17)-Flujo!L$21*(1+$B17)+Flujo!L$22*IF(Supuestos!$B$31="valor_libro",1+$D17,1) -> 90665705 | P17: =E17+NPV(Supuestos!$B$4,F17:O17) -> -9450286.4
A19: Sensibilidad a la tasa de descuento
A20: Tasa 8.0% | B20: =Supuestos!$B$4+(-0.02) -> 0.08 | C20: =Flujo!$B$23+NPV(B20,Flujo!$C$23:$L$23) -> 52127672
A21: Tasa 9.0% | B21: =Supuestos!$B$4+(-0.01) -> 0.09 | C21: =Flujo!$B$23+NPV(B21,Flujo!$C$23:$L$23) -> 39053965
A22: Tasa 10.0% | B22: =Supuestos!$B$4+(0) -> 0.1 | C22: =Flujo!$B$23+NPV(B22,Flujo!$C$23:$L$23) -> 26908200
A23: Tasa 11.0% | B23: =Supuestos!$B$4+(0.01) -> 0.11 | C23: =Flujo!$B$23+NPV(B23,Flujo!$C$23:$L$23) -> 15610218
A24: Tasa 12.0% | B24: =Supuestos!$B$4+(0.02) -> 0.12 | C24: =Flujo!$B$23+NPV(B24,Flujo!$C$23:$L$23) -> 5087748.8
