Workbook

Sheet Parametros
A1: Parámetros de las bases — Riego inteligente AgroSur
A2: Azul = entrada tomada de las bases (vacío = las bases no fijan esa regla). La fuente es presupuesto.yaml: este Excel sirve para revisar y simular; los cambios definitivos van al YAML.
A3: Parámetro | B3: Valor | C3: Fuente
A4: Financiamiento máximo de la entidad (% del costo total) | B4: 0.7 | C4: Bases B01, numeral 3
A5: Financiamiento máximo de la entidad (monto) | B5: 40000000 | C5: Bases B01, numeral 3
A6: Aporte propio mínimo (% del costo total) | B6: 0.3 | C6: Bases B01, numeral 3
A7: Aporte pecuniario mínimo (% del aporte propio) | B7: 0.5 | C7: Bases B01, numeral 3
A9: Ítems de gasto
A10: Ítem | B10: Nombre | C10: Tope (% del costo total)
A11: RRHH | B11: Recursos humanos
A12: OPE | B12: Gastos de operación
A13: INV | B13: Inversión
A14: ADM | B14: Gastos de administración | C14: 0.1

Sheet Presupuesto
A1: Presupuesto — Riego inteligente AgroSur (CLP)
A2: Azul = entrada. Las fuentes de cada partida son fracciones que deben sumar 100%.
A3: Ítem | B3: Descripción | C3: Unidad | D3: Cantidad | E3: Costo unitario | F3: Costo total | G3: % Entidad | H3: % Propio pecuniario | I3: % Propio no pecuniario | J3: % Terceros | K3: Suma % | L3: Entidad | M3: Propio pecuniario | N3: Propio no pecuniario | O3: Terceros
A4: RRHH | B4: Directora del proyecto (horas del equipo AgroSur) | C4: mes | D4: 12 | E4: 1000000 | F4: =D4*E4 | G4: 0 | H4: 0 | I4: 1 | J4: 0 | K4: =SUM(G4:J4) | L4: =$F4*G4 | M4: =$F4*H4 | N4: =$F4*I4 | O4: =$F4*J4
A5: RRHH | B5: Ingeniero IoT | C5: mes | D5: 12 | E5: 1500000 | F5: =D5*E5 | G5: 1 | H5: 0 | I5: 0 | J5: 0 | K5: =SUM(G5:J5) | L5: =$F5*G5 | M5: =$F5*H5 | N5: =$F5*I5 | O5: =$F5*J5
A6: INV | B6: Sensores y gateways | C6: unidad | D6: 60 | E6: 150000 | F6: =D6*E6 | G6: 1 | H6: 0 | I6: 0 | J6: 0 | K6: =SUM(G6:J6) | L6: =$F6*G6 | M6: =$F6*H6 | N6: =$F6*I6 | O6: =$F6*J6
A7: OPE | B7: Validación en 6 predios | C7: predio | D7: 6 | E7: 1000000 | F7: =D7*E7 | G7: 1 | H7: 0 | I7: 0 | J7: 0 | K7: =SUM(G7:J7) | L7: =$F7*G7 | M7: =$F7*H7 | N7: =$F7*I7 | O7: =$F7*J7
A8: OPE | B8: Uso de oficina y bodega (valorizado) | C8: global | D8: 1 | E8: 1000000 | F8: =D8*E8 | G8: 0 | H8: 0 | I8: 1 | J8: 0 | K8: =SUM(G8:J8) | L8: =$F8*G8 | M8: =$F8*H8 | N8: =$F8*I8 | O8: =$F8*J8
A9: OPE | B9: Difusión y capacitación a productores | C9: global | D9: 1 | E9: 4000000 | F9: =D9*E9 | G9: 1 | H9: 0 | I9: 0 | J9: 0 | K9: =SUM(G9:J9) | L9: =$F9*G9 | M9: =$F9*H9 | N9: =$F9*I9 | O9: =$F9*J9
A10: ADM | B10: Administración del proyecto | C10: global | D10: 1 | E10: 5000000 | F10: =D10*E10 | G10: 0.6 | H10: 0.4 | I10: 0 | J10: 0 | K10: =SUM(G10:J10) | L10: =$F10*G10 | M10: =$F10*H10 | N10: =$F10*I10 | O10: =$F10*J10
B11: Total | F11: =SUM(F4:F10) | L11: =SUM(L4:L10) | M11: =SUM(M4:M10) | N11: =SUM(N4:N10) | O11: =SUM(O4:O10)

Sheet Resumen
A1: Resumen por ítem y por fuente
A3: Ítem | B3: Nombre | C3: Costo total | D3: % del total | E3: Tope | F3: Estado | G3: Entidad | H3: Propio pecuniario | I3: Propio no pecuniario | J3: Terceros
A4: =Parametros!A11 | B4: =Parametros!B11 | C4: =SUMIF(Presupuesto!$A$4:$A$10,A4,Presupuesto!$F$4:$F$10) | D4: =IFERROR(C4/Presupuesto!$F$11,0) | E4: =IF(Parametros!C11="","",Parametros!C11) | F4: =IF(E4="","SIN TOPE",IF(D4<=E4+0.0000001,"CUMPLE","NO CUMPLE")) | G4: =SUMIF(Presupuesto!$A$4:$A$10,A4,Presupuesto!$L$4:$L$10) | H4: =SUMIF(Presupuesto!$A$4:$A$10,A4,Presupuesto!$M$4:$M$10) | I4: =SUMIF(Presupuesto!$A$4:$A$10,A4,Presupuesto!$N$4:$N$10) | J4: =SUMIF(Presupuesto!$A$4:$A$10,A4,Presupuesto!$O$4:$O$10)
A5: =Parametros!A12 | B5: =Parametros!B12 | C5: =SUMIF(Presupuesto!$A$4:$A$10,A5,Presupuesto!$F$4:$F$10) | D5: =IFERROR(C5/Presupuesto!$F$11,0) | E5: =IF(Parametros!C12="","",Parametros!C12) | F5: =IF(E5="","SIN TOPE",IF(D5<=E5+0.0000001,"CUMPLE","NO CUMPLE")) | G5: =SUMIF(Presupuesto!$A$4:$A$10,A5,Presupuesto!$L$4:$L$10) | H5: =SUMIF(Presupuesto!$A$4:$A$10,A5,Presupuesto!$M$4:$M$10) | I5: =SUMIF(Presupuesto!$A$4:$A$10,A5,Presupuesto!$N$4:$N$10) | J5: =SUMIF(Presupuesto!$A$4:$A$10,A5,Presupuesto!$O$4:$O$10)
A6: =Parametros!A13 | B6: =Parametros!B13 | C6: =SUMIF(Presupuesto!$A$4:$A$10,A6,Presupuesto!$F$4:$F$10) | D6: =IFERROR(C6/Presupuesto!$F$11,0) | E6: =IF(Parametros!C13="","",Parametros!C13) | F6: =IF(E6="","SIN TOPE",IF(D6<=E6+0.0000001,"CUMPLE","NO CUMPLE")) | G6: =SUMIF(Presupuesto!$A$4:$A$10,A6,Presupuesto!$L$4:$L$10) | H6: =SUMIF(Presupuesto!$A$4:$A$10,A6,Presupuesto!$M$4:$M$10) | I6: =SUMIF(Presupuesto!$A$4:$A$10,A6,Presupuesto!$N$4:$N$10) | J6: =SUMIF(Presupuesto!$A$4:$A$10,A6,Presupuesto!$O$4:$O$10)
A7: =Parametros!A14 | B7: =Parametros!B14 | C7: =SUMIF(Presupuesto!$A$4:$A$10,A7,Presupuesto!$F$4:$F$10) | D7: =IFERROR(C7/Presupuesto!$F$11,0) | E7: =IF(Parametros!C14="","",Parametros!C14) | F7: =IF(E7="","SIN TOPE",IF(D7<=E7+0.0000001,"CUMPLE","NO CUMPLE")) | G7: =SUMIF(Presupuesto!$A$4:$A$10,A7,Presupuesto!$L$4:$L$10) | H7: =SUMIF(Presupuesto!$A$4:$A$10,A7,Presupuesto!$M$4:$M$10) | I7: =SUMIF(Presupuesto!$A$4:$A$10,A7,Presupuesto!$N$4:$N$10) | J7: =SUMIF(Presupuesto!$A$4:$A$10,A7,Presupuesto!$O$4:$O$10)
A9: Por fuente
A10: Fuente | C10: Monto | D10: % del total
A11: Entidad | C11: =Presupuesto!L11 | D11: =IFERROR(C11/Presupuesto!$F$11,0)
A12: Propio pecuniario | C12: =Presupuesto!M11 | D12: =IFERROR(C12/Presupuesto!$F$11,0)
A13: Propio no pecuniario | C13: =Presupuesto!N11 | D13: =IFERROR(C13/Presupuesto!$F$11,0)
A14: Terceros | C14: =Presupuesto!O11 | D14: =IFERROR(C14/Presupuesto!$F$11,0)
A15: Aporte propio total | C15: =C12+C13 | D15: =IFERROR(C15/Presupuesto!$F$11,0)
A16: Costo total | C16: =Presupuesto!$F$11

Sheet Controles
A1: Controles contra las bases
A2: Se recalculan solos al cambiar parámetros o partidas. NO CUMPLE debe quedar en cero antes de postular.
A3: Id | B3: Control | C3: Valor | D3: Límite | E3: Estado | F3: Fuente
A4: CTL-00 | B4: Costo total del presupuesto mayor que cero | C4: =Presupuesto!$F$11 | D4: 0 | E4: =IF(C4>0,"CUMPLE","NO CUMPLE") | F4: Coherencia interna
A5: CTL-01 | B5: Aporte de la entidad / costo total ≤ máximo | C5: =IFERROR(Resumen!C11/Presupuesto!$F$11,0) | D5: =IF(Parametros!B4="","",Parametros!B4) | E5: =IF(D5="","SIN REGLA",IF(Presupuesto!$F$11<=0,"SIN DATOS",IF(C5<=D5+0.0000001,"CUMPLE","NO CUMPLE"))) | F5: =Parametros!C4
A6: CTL-02 | B6: Aporte de la entidad ≤ monto máximo | C6: =Resumen!C11 | D6: =IF(Parametros!B5="","",Parametros!B5) | E6: =IF(D6="","SIN REGLA",IF(Presupuesto!$F$11<=0,"SIN DATOS",IF(C6<=D6+0.0000001,"CUMPLE","NO CUMPLE"))) | F6: =Parametros!C4
A7: CTL-03 | B7: Aporte propio / costo total ≥ mínimo | C7: =Resumen!D15 | D7: =IF(Parametros!B6="","",Parametros!B6) | E7: =IF(D7="","SIN REGLA",IF(Presupuesto!$F$11<=0,"SIN DATOS",IF(C7>=D7-0.0000001,"CUMPLE","NO CUMPLE"))) | F7: =Parametros!C4
A8: CTL-04 | B8: Aporte pecuniario / aporte propio ≥ mínimo | C8: =IFERROR(Resumen!C12/Resumen!C15,0) | D8: =IF(Parametros!B7="","",Parametros!B7) | E8: =IF(D8="","SIN REGLA",IF(Presupuesto!$F$11<=0,"SIN DATOS",IF(C8>=D8-0.0000001,"CUMPLE","NO CUMPLE"))) | F8: =Parametros!C4
A9: CTL-05 | B9: Partidas cuyas fuentes no suman 100% | C9: =SUMPRODUCT(--(ABS(Presupuesto!K4:K10-1)>0.0001))*(Presupuesto!$F$11>0) | D9: 0 | E9: =IF(C9=0,"CUMPLE","NO CUMPLE") | F9: Coherencia interna
A10: CTL-06 | B10: ="Ítem "&Resumen!A4&" ("&Resumen!B4&") / costo total ≤ tope" | C10: =Resumen!D4 | D10: =Resumen!E4 | E10: =IF(D10="","SIN REGLA",IF(Presupuesto!$F$11<=0,"SIN DATOS",IF(C10<=D10+0.0000001,"CUMPLE","NO CUMPLE"))) | F10: =Parametros!C4
A11: CTL-07 | B11: ="Ítem "&Resumen!A5&" ("&Resumen!B5&") / costo total ≤ tope" | C11: =Resumen!D5 | D11: =Resumen!E5 | E11: =IF(D11="","SIN REGLA",IF(Presupuesto!$F$11<=0,"SIN DATOS",IF(C11<=D11+0.0000001,"CUMPLE","NO CUMPLE"))) | F11: =Parametros!C4
A12: CTL-08 | B12: ="Ítem "&Resumen!A6&" ("&Resumen!B6&") / costo total ≤ tope" | C12: =Resumen!D6 | D12: =Resumen!E6 | E12: =IF(D12="","SIN REGLA",IF(Presupuesto!$F$11<=0,"SIN DATOS",IF(C12<=D12+0.0000001,"CUMPLE","NO CUMPLE"))) | F12: =Parametros!C4
A13: CTL-09 | B13: ="Ítem "&Resumen!A7&" ("&Resumen!B7&") / costo total ≤ tope" | C13: =Resumen!D7 | D13: =Resumen!E7 | E13: =IF(D13="","SIN REGLA",IF(Presupuesto!$F$11<=0,"SIN DATOS",IF(C13<=D13+0.0000001,"CUMPLE","NO CUMPLE"))) | F13: =Parametros!C4
B15: Controles NO CUMPLE | C15: =COUNTIF(E4:E13,"NO CUMPLE")

Sheet Cronograma
A1: Cronograma financiero (distribución mensual de cada partida)
A2: Azul = % del costo de la partida que se ejecuta cada mes (debe sumar 100%).
A3: Partida | B3: Costo total | C3: Mes 1 | D3: Mes 2 | E3: Mes 3 | F3: Mes 4 | G3: Mes 5 | H3: Mes 6 | I3: Mes 7 | J3: Mes 8 | K3: Mes 9 | L3: Mes 10 | M3: Mes 11 | N3: Mes 12 | O3: Suma %
A4: =Presupuesto!B4 | B4: =Presupuesto!F4 | C4: 0.083333 | D4: 0.083333 | E4: 0.083333 | F4: 0.083333 | G4: 0.083333 | H4: 0.083333 | I4: 0.083333 | J4: 0.083333 | K4: 0.083333 | L4: 0.083333 | M4: 0.083333 | N4: 0.083333 | O4: =SUM(C4:N4)
A5: =Presupuesto!B5 | B5: =Presupuesto!F5 | C5: 0.083333 | D5: 0.083333 | E5: 0.083333 | F5: 0.083333 | G5: 0.083333 | H5: 0.083333 | I5: 0.083333 | J5: 0.083333 | K5: 0.083333 | L5: 0.083333 | M5: 0.083333 | N5: 0.083333 | O5: =SUM(C5:N5)
A6: =Presupuesto!B6 | B6: =Presupuesto!F6 | C6: 0.083333 | D6: 0.083333 | E6: 0.083333 | F6: 0.083333 | G6: 0.083333 | H6: 0.083333 | I6: 0.083333 | J6: 0.083333 | K6: 0.083333 | L6: 0.083333 | M6: 0.083333 | N6: 0.083333 | O6: =SUM(C6:N6)
A7: =Presupuesto!B7 | B7: =Presupuesto!F7 | C7: 0.083333 | D7: 0.083333 | E7: 0.083333 | F7: 0.083333 | G7: 0.083333 | H7: 0.083333 | I7: 0.083333 | J7: 0.083333 | K7: 0.083333 | L7: 0.083333 | M7: 0.083333 | N7: 0.083333 | O7: =SUM(C7:N7)
A8: =Presupuesto!B8 | B8: =Presupuesto!F8 | C8: 0.083333 | D8: 0.083333 | E8: 0.083333 | F8: 0.083333 | G8: 0.083333 | H8: 0.083333 | I8: 0.083333 | J8: 0.083333 | K8: 0.083333 | L8: 0.083333 | M8: 0.083333 | N8: 0.083333 | O8: =SUM(C8:N8)
A9: =Presupuesto!B9 | B9: =Presupuesto!F9 | C9: 0.083333 | D9: 0.083333 | E9: 0.083333 | F9: 0.083333 | G9: 0.083333 | H9: 0.083333 | I9: 0.083333 | J9: 0.083333 | K9: 0.083333 | L9: 0.083333 | M9: 0.083333 | N9: 0.083333 | O9: =SUM(C9:N9)
A10: =Presupuesto!B10 | B10: =Presupuesto!F10 | C10: 0.083333 | D10: 0.083333 | E10: 0.083333 | F10: 0.083333 | G10: 0.083333 | H10: 0.083333 | I10: 0.083333 | J10: 0.083333 | K10: 0.083333 | L10: 0.083333 | M10: 0.083333 | N10: 0.083333 | O10: =SUM(C10:N10)
A13: Montos por mes
A14: =A4 | C14: =$B4*C4 | D14: =$B4*D4 | E14: =$B4*E4 | F14: =$B4*F4 | G14: =$B4*G4 | H14: =$B4*H4 | I14: =$B4*I4 | J14: =$B4*J4 | ... N14: =$B4*N4
A15: =A5 | C15: =$B5*C5 | D15: =$B5*D5 | E15: =$B5*E5 | F15: =$B5*F5 | G15: =$B5*G5 | H15: =$B5*H5 | I15: =$B5*I5 | J15: =$B5*J5 | ... N15: =$B5*N5
A16: =A6 | C16: =$B6*C6 | D16: =$B6*D6 | E16: =$B6*E6 | F16: =$B6*F6 | G16: =$B6*G6 | H16: =$B6*H6 | I16: =$B6*I6 | J16: =$B6*J6 | ... N16: =$B6*N6
A17: =A7 | C17: =$B7*C7 | D17: =$B7*D7 | E17: =$B7*E7 | F17: =$B7*F7 | G17: =$B7*G7 | H17: =$B7*H7 | I17: =$B7*I7 | J17: =$B7*J7 | ... N17: =$B7*N7
A18: =A8 | C18: =$B8*C8 | D18: =$B8*D8 | E18: =$B8*E8 | F18: =$B8*F8 | G18: =$B8*G8 | H18: =$B8*H8 | I18: =$B8*I8 | J18: =$B8*J8 | ... N18: =$B8*N8
A19: =A9 | C19: =$B9*C9 | D19: =$B9*D9 | E19: =$B9*E9 | F19: =$B9*F9 | G19: =$B9*G9 | H19: =$B9*H9 | I19: =$B9*I9 | J19: =$B9*J9 | ... N19: =$B9*N9
A20: =A10 | C20: =$B10*C10 | D20: =$B10*D10 | E20: =$B10*E10 | F20: =$B10*F10 | G20: =$B10*G10 | H20: =$B10*H10 | I20: =$B10*I10 | J20: =$B10*J10 | ... N20: =$B10*N10
A21: Total mes | C21: =SUM(C14:C20) | D21: =SUM(D14:D20) | E21: =SUM(E14:E20) | F21: =SUM(F14:F20) | G21: =SUM(G14:G20) | H21: =SUM(H14:H20) | I21: =SUM(I14:I20) | J21: =SUM(J14:J20) | ... N21: =SUM(N14:N20)
